{"jobId":[527135317],"playerStats":{"player":[{"rebounds":[2],"penalties":[3],"gain":[0],"possessions":[15],"offensiveRebounds":[2],"goalMisses":[3],"blocked":[0],"passes":[2],"goalAssists":[2],"disposals":[14],"tossUpWin":[0],"centrePassReceives":[0],"obstructionPenalties":[1],"feeds":[2],"playerId":[80469],"goals":[8],"offsides":[0],"badPasses":[0],"defensiveRebounds":[0],"breaks":[0],"blocks":[0],"badHands":[1],"missedGoalTurnover":[0],"squadId":[802],"startingPositionCode":["GS"],"goalAttempts":[11],"deflections":[0],"contactPenalties":[2],"quartersPlayed":[2],"minutesPlayed":[26],"turnovers":[2],"pickups":[1],"currentPositionCode":["-"],"intercepts":[0]},{"rebounds":[0],"penalties":[2],"gain":[0],"possessions":[25],"offensiveRebounds":[0],"goalMisses":[2],"blocked":[0],"passes":[8],"goalAssists":[4],"disposals":[22],"tossUpWin":[0],"centrePassReceives":[11],"obstructionPenalties":[0],"feeds":[8],"playerId":[80028],"goals":[10],"offsides":[0],"badPasses":[0],"defensiveRebounds":[0],"breaks":[0],"blocks":[0],"badHands":[1],"missedGoalTurnover":[0],"squadId":[802],"startingPositionCode":["GA"],"goalAttempts":[12],"deflections":[0],"contactPenalties":[2],"quartersPlayed":[4],"minutesPlayed":[47],"turnovers":[6],"pickups":[0],"currentPositionCode":["GA"],"intercepts":[0]},{"rebounds":[0],"penalties":[6],"gain":[0],"possessions":[23],"offensiveRebounds":[0],"goalMisses":[0],"blocked":[0],"passes":[40],"goalAssists":[18],"disposals":[43],"tossUpWin":[0],"centrePassReceives":[20],"obstructionPenalties":[2],"feeds":[40],"playerId":[80699],"goals":[0],"offsides":[0],"badPasses":[2],"defensiveRebounds":[0],"breaks":[0],"blocks":[0],"badHands":[1],"missedGoalTurnover":[0],"squadId":[802],"startingPositionCode":["WA"],"goalAttempts":[0],"deflections":[0],"contactPenalties":[4],"quartersPlayed":[4],"minutesPlayed":[60],"turnovers":[3],"pickups":[0],"currentPositionCode":["WA"],"intercepts":[0]},{"rebounds":[0],"penalties":[10],"gain":[1],"possessions":[3],"offensiveRebounds":[0],"goalMisses":[0],"blocked":[0],"passes":[36],"goalAssists":[8],"disposals":[36],"tossUpWin":[0],"centrePassReceives":[0],"obstructionPenalties":[3],"feeds":[36],"playerId":[80526],"goals":[0],"offsides":[1],"badPasses":[2],"defensiveRebounds":[0],"breaks":[0],"blocks":[0],"badHands":[0],"missedGoalTurnover":[0],"squadId":[802],"startingPositionCode":["C"],"goalAttempts":[0],"deflections":[0],"contactPenalties":[7],"quartersPlayed":[4],"minutesPlayed":[57],"turnovers":[3],"pickups":[1],"currentPositionCode":["-"],"intercepts":[1]},{"rebounds":[0],"penalties":[7],"gain":[1],"possessions":[10],"offensiveRebounds":[0],"goalMisses":[0],"blocked":[0],"passes":[2],"goalAssists":[0],"disposals":[2],"tossUpWin":[0],"centrePassReceives":[6],"obstructionPenalties":[1],"feeds":[2],"playerId":[80223],"goals":[0],"offsides":[1],"badPasses":[1],"defensiveRebounds":[0],"breaks":[1],"blocks":[0],"badHands":[1],"missedGoalTurnover":[0],"squadId":[802],"startingPositionCode":["WD"],"goalAttempts":[0],"deflections":[1],"contactPenalties":[6],"quartersPlayed":[4],"minutesPlayed":[60],"turnovers":[2],"pickups":[2],"currentPositionCode":["WD"],"intercepts":[1]},{"rebounds":[4],"penalties":[17],"gain":[5],"possessions":[11],"offensiveRebounds":[0],"goalMisses":[0],"blocked":[0],"passes":[0],"goalAssists":[0],"disposals":[1],"tossUpWin":[0],"centrePassReceives":[4],"obstructionPenalties":[2],"feeds":[0],"playerId":[80524],"goals":[0],"offsides":[0],"badPasses":[0],"defensiveRebounds":[4],"breaks":[0],"blocks":[0],"badHands":[0],"missedGoalTurnover":[0],"squadId":[802],"startingPositionCode":["GD"],"goalAttempts":[0],"deflections":[3],"contactPenalties":[15],"quartersPlayed":[4],"minutesPlayed":[60],"turnovers":[0],"pickups":[1],"currentPositionCode":["GD"],"intercepts":[0]},{"rebounds":[2],"penalties":[11],"gain":[12],"possessions":[17],"offensiveRebounds":[0],"goalMisses":[0],"blocked":[0],"passes":[0],"goalAssists":[0],"disposals":[7],"tossUpWin":[0],"centrePassReceives":[0],"obstructionPenalties":[4],"feeds":[0],"playerId":[80604],"goals":[0],"offsides":[0],"badPasses":[0],"defensiveRebounds":[2],"breaks":[0],"blocks":[0],"badHands":[0],"missedGoalTurnover":[0],"squadId":[802],"startingPositionCode":["GK"],"goalAttempts":[0],"deflections":[8],"contactPenalties":[7],"quartersPlayed":[4],"minutesPlayed":[60],"turnovers":[0],"pickups":[1],"currentPositionCode":["GK"],"intercepts":[7]},{"rebounds":[1],"penalties":[4],"gain":[0],"possessions":[40],"offensiveRebounds":[1],"goalMisses":[9],"blocked":[0],"passes":[6],"goalAssists":[2],"disposals":[42],"tossUpWin":[0],"centrePassReceives":[3],"obstructionPenalties":[0],"feeds":[6],"playerId":[80532],"goals":[26],"offsides":[0],"badPasses":[2],"defensiveRebounds":[0],"breaks":[0],"blocks":[0],"badHands":[1],"missedGoalTurnover":[0],"squadId":[802],"startingPositionCode":["-"],"goalAttempts":[35],"deflections":[0],"contactPenalties":[4],"quartersPlayed":[4],"minutesPlayed":[48],"turnovers":[11],"pickups":[0],"currentPositionCode":["GS"],"intercepts":[0]},{"rebounds":[0],"penalties":[1],"gain":[0],"possessions":[0],"offensiveRebounds":[0],"goalMisses":[0],"blocked":[0],"passes":[3],"goalAssists":[0],"disposals":[3],"tossUpWin":[0],"centrePassReceives":[0],"obstructionPenalties":[1],"feeds":[3],"playerId":[997432],"goals":[0],"offsides":[0],"badPasses":[0],"defensiveRebounds":[0],"breaks":[0],"blocks":[0],"badHands":[0],"missedGoalTurnover":[0],"squadId":[802],"startingPositionCode":["-"],"goalAttempts":[0],"deflections":[0],"contactPenalties":[0],"quartersPlayed":[1],"minutesPlayed":[4],"turnovers":[0],"pickups":[0],"currentPositionCode":["C"],"intercepts":[0]},{"rebounds":[0],"penalties":[0],"gain":[0],"possessions":[0],"offensiveRebounds":[0],"goalMisses":[0],"blocked":[0],"passes":[0],"goalAssists":[0],"disposals":[0],"tossUpWin":[0],"centrePassReceives":[0],"obstructionPenalties":[0],"feeds":[0],"playerId":[999790],"goals":[0],"offsides":[0],"badPasses":[0],"defensiveRebounds":[0],"breaks":[0],"blocks":[0],"badHands":[0],"missedGoalTurnover":[0],"squadId":[802],"startingPositionCode":["-"],"goalAttempts":[0],"deflections":[0],"contactPenalties":[0],"quartersPlayed":[0],"minutesPlayed":[0],"turnovers":[0],"pickups":[0],"currentPositionCode":["-"],"intercepts":[0]},{"rebounds":[3],"penalties":[1],"gain":[0],"possessions":[40],"offensiveRebounds":[3],"goalMisses":[5],"blocked":[0],"passes":[5],"goalAssists":[3],"disposals":[42],"tossUpWin":[0],"centrePassReceives":[0],"obstructionPenalties":[1],"feeds":[5],"playerId":[80710],"goals":[32],"offsides":[0],"badPasses":[0],"defensiveRebounds":[0],"breaks":[0],"blocks":[0],"badHands":[1],"missedGoalTurnover":[0],"squadId":[8120],"startingPositionCode":["GS"],"goalAttempts":[37],"deflections":[0],"contactPenalties":[0],"quartersPlayed":[4],"minutesPlayed":[60],"turnovers":[5],"pickups":[0],"currentPositionCode":["GS"],"intercepts":[0]},{"rebounds":[0],"penalties":[5],"gain":[0],"possessions":[38],"offensiveRebounds":[0],"goalMisses":[6],"blocked":[0],"passes":[14],"goalAssists":[10],"disposals":[42],"tossUpWin":[0],"centrePassReceives":[9],"obstructionPenalties":[3],"feeds":[14],"playerId":[991906],"goals":[17],"offsides":[0],"badPasses":[1],"defensiveRebounds":[0],"breaks":[0],"blocks":[0],"badHands":[0],"missedGoalTurnover":[0],"squadId":[8120],"startingPositionCode":["GA"],"goalAttempts":[23],"deflections":[1],"contactPenalties":[2],"quartersPlayed":[4],"minutesPlayed":[56],"turnovers":[5],"pickups":[1],"currentPositionCode":["GA"],"intercepts":[0]},{"rebounds":[0],"penalties":[5],"gain":[1],"possessions":[15],"offensiveRebounds":[0],"goalMisses":[0],"blocked":[0],"passes":[17],"goalAssists":[6],"disposals":[17],"tossUpWin":[0],"centrePassReceives":[13],"obstructionPenalties":[2],"feeds":[17],"playerId":[80214],"goals":[0],"offsides":[1],"badPasses":[1],"defensiveRebounds":[0],"breaks":[0],"blocks":[0],"badHands":[0],"missedGoalTurnover":[0],"squadId":[8120],"startingPositionCode":["WA"],"goalAttempts":[0],"deflections":[0],"contactPenalties":[3],"quartersPlayed":[4],"minutesPlayed":[47],"turnovers":[3],"pickups":[1],"currentPositionCode":["WA"],"intercepts":[1]},{"rebounds":[0],"penalties":[3],"gain":[1],"possessions":[11],"offensiveRebounds":[0],"goalMisses":[0],"blocked":[0],"passes":[25],"goalAssists":[10],"disposals":[26],"tossUpWin":[0],"centrePassReceives":[8],"obstructionPenalties":[1],"feeds":[25],"playerId":[80182],"goals":[0],"offsides":[0],"badPasses":[1],"defensiveRebounds":[0],"breaks":[0],"blocks":[0],"badHands":[1],"missedGoalTurnover":[0],"squadId":[8120],"startingPositionCode":["C"],"goalAttempts":[0],"deflections":[1],"contactPenalties":[2],"quartersPlayed":[4],"minutesPlayed":[60],"turnovers":[2],"pickups":[2],"currentPositionCode":["C"],"intercepts":[0]},{"rebounds":[0],"penalties":[15],"gain":[2],"possessions":[15],"offensiveRebounds":[0],"goalMisses":[0],"blocked":[0],"passes":[0],"goalAssists":[0],"disposals":[1],"tossUpWin":[0],"centrePassReceives":[13],"obstructionPenalties":[6],"feeds":[0],"playerId":[80304],"goals":[0],"offsides":[0],"badPasses":[2],"defensiveRebounds":[0],"breaks":[1],"blocks":[0],"badHands":[0],"missedGoalTurnover":[0],"squadId":[8120],"startingPositionCode":["WD"],"goalAttempts":[0],"deflections":[3],"contactPenalties":[9],"quartersPlayed":[4],"minutesPlayed":[60],"turnovers":[3],"pickups":[0],"currentPositionCode":["WD"],"intercepts":[1]},{"rebounds":[3],"penalties":[8],"gain":[6],"possessions":[15],"offensiveRebounds":[0],"goalMisses":[0],"blocked":[0],"passes":[2],"goalAssists":[1],"disposals":[4],"tossUpWin":[0],"centrePassReceives":[1],"obstructionPenalties":[0],"feeds":[2],"playerId":[80057],"goals":[0],"offsides":[0],"badPasses":[0],"defensiveRebounds":[3],"breaks":[0],"blocks":[0],"badHands":[0],"missedGoalTurnover":[0],"squadId":[8120],"startingPositionCode":["GD"],"goalAttempts":[0],"deflections":[4],"contactPenalties":[8],"quartersPlayed":[4],"minutesPlayed":[60],"turnovers":[0],"pickups":[3],"currentPositionCode":["GD"],"intercepts":[3]},{"rebounds":[6],"penalties":[9],"gain":[8],"possessions":[16],"offensiveRebounds":[0],"goalMisses":[0],"blocked":[0],"passes":[0],"goalAssists":[0],"disposals":[6],"tossUpWin":[0],"centrePassReceives":[0],"obstructionPenalties":[3],"feeds":[0],"playerId":[80305],"goals":[0],"offsides":[0],"badPasses":[0],"defensiveRebounds":[6],"breaks":[0],"blocks":[0],"badHands":[0],"missedGoalTurnover":[0],"squadId":[8120],"startingPositionCode":["GK"],"goalAttempts":[0],"deflections":[2],"contactPenalties":[6],"quartersPlayed":[4],"minutesPlayed":[60],"turnovers":[0],"pickups":[1],"currentPositionCode":["GK"],"intercepts":[2]},{"rebounds":[0],"penalties":[0],"gain":[0],"possessions":[0],"offensiveRebounds":[0],"goalMisses":[0],"blocked":[0],"passes":[0],"goalAssists":[0],"disposals":[0],"tossUpWin":[0],"centrePassReceives":[0],"obstructionPenalties":[0],"feeds":[0],"playerId":[80808],"goals":[0],"offsides":[0],"badPasses":[0],"defensiveRebounds":[0],"breaks":[0],"blocks":[0],"badHands":[0],"missedGoalTurnover":[0],"squadId":[8120],"startingPositionCode":["-"],"goalAttempts":[0],"deflections":[0],"contactPenalties":[0],"quartersPlayed":[0],"minutesPlayed":[0],"turnovers":[0],"pickups":[0],"currentPositionCode":["-"],"intercepts":[0]},{"rebounds":[0],"penalties":[3],"gain":[0],"possessions":[0],"offensiveRebounds":[0],"goalMisses":[0],"blocked":[0],"passes":[9],"goalAssists":[4],"disposals":[9],"tossUpWin":[0],"centrePassReceives":[0],"obstructionPenalties":[0],"feeds":[9],"playerId":[998998],"goals":[0],"offsides":[0],"badPasses":[1],"defensiveRebounds":[0],"breaks":[0],"blocks":[0],"badHands":[0],"missedGoalTurnover":[0],"squadId":[8120],"startingPositionCode":["-"],"goalAttempts":[0],"deflections":[1],"contactPenalties":[3],"quartersPlayed":[2],"minutesPlayed":[14],"turnovers":[2],"pickups":[0],"currentPositionCode":["-"],"intercepts":[0]},{"rebounds":[0],"penalties":[1],"gain":[0],"possessions":[2],"offensiveRebounds":[0],"goalMisses":[1],"blocked":[0],"passes":[0],"goalAssists":[0],"disposals":[1],"tossUpWin":[0],"centrePassReceives":[1],"obstructionPenalties":[0],"feeds":[0],"playerId":[80229],"goals":[0],"offsides":[0],"badPasses":[0],"defensiveRebounds":[0],"breaks":[0],"blocks":[0],"badHands":[0],"missedGoalTurnover":[0],"squadId":[8120],"startingPositionCode":["-"],"goalAttempts":[1],"deflections":[0],"contactPenalties":[1],"quartersPlayed":[1],"minutesPlayed":[5],"turnovers":[2],"pickups":[0],"currentPositionCode":["-"],"intercepts":[0]}]},"matchInfo":{"period":[4],"matchType":["H"],"finalCode":[""],"homeSquadId":[802],"periodCompleted":[4],"finalShortCode":[""],"venueName":["ILT Stadium Southland"],"matchStatus":["complete"],"roundNumber":[6],"utcStartTime":["2017-04-30T06:00:00Z"],"venueId":[813],"periodSeconds":[906],"awaySquadId":[8120],"venueCode":["SOU"],"localStartTime":["2017-04-30T18:00:00+12:00"],"matchId":[100880603],"matchNumber":[3]},"playerInfo":{"player":[{"shortDisplayName":["Leaver, B"],"firstname":["Brooke"],"surname":["Leaver"],"displayName":["B.Leaver"],"playerId":[80469]},{"shortDisplayName":["Thompson, A"],"firstname":["Anna"],"surname":["Thompson"],"displayName":["A.Thompson"],"playerId":[80028]},{"shortDisplayName":["Pedersen, E"],"firstname":["Erikana"],"surname":["Pedersen"],"displayName":["E.Pedersen"],"playerId":[80699]},{"shortDisplayName":["Mackle, N"],"firstname":["Nicola"],"surname":["Mackle"],"displayName":["N.Mackle"],"playerId":[80526]},{"shortDisplayName":["Saunders, H"],"firstname":["Hayley"],"surname":["Saunders"],"displayName":["H.Saunders"],"playerId":[80223]},{"shortDisplayName":["Walker, Z"],"firstname":["Zoe"],"surname":["Walker"],"displayName":["Z.Walker"],"playerId":[80524]},{"shortDisplayName":["Fakahokotau, T"],"firstname":["Temalisi"],"surname":["Fakahokotau"],"displayName":["T.Fakahokotau"],"playerId":[80604]},{"shortDisplayName":["Corbin, K"],"firstname":["Kadeen"],"surname":["Corbin"],"displayName":["K.Corbin"],"playerId":[80532]},{"shortDisplayName":["Elley, C"],"firstname":["Charlotte"],"surname":["Elley"],"displayName":["C.Elley"],"playerId":[997432]},{"shortDisplayName":["Lloyd, K"],"firstname":["Kate"],"surname":["Lloyd"],"displayName":["K.Lloyd"],"playerId":[999790]},{"shortDisplayName":["Wilson, M"],"firstname":["Maia"],"surname":["Wilson"],"displayName":["M.Wilson"],"playerId":[80710]},{"shortDisplayName":["Vaka, M"],"firstname":["Malia"],"surname":["Vaka"],"displayName":["M.Vaka"],"playerId":[991906]},{"shortDisplayName":["Iversen, E"],"firstname":["Emma"],"surname":["Iversen"],"displayName":["E.Iversen"],"playerId":[80214]},{"shortDisplayName":["Tairi, C"],"firstname":["Courtney"],"surname":["Tairi"],"displayName":["C.Tairi"],"playerId":[80182]},{"shortDisplayName":["Cullen, K"],"firstname":["Kayla"],"surname":["Cullen"],"displayName":["K.Cullen"],"playerId":[80304]},{"shortDisplayName":["de Bruin, L"],"firstname":["Leana"],"surname":["de Bruin"],"displayName":["L.de Bruin"],"playerId":[80057]},{"shortDisplayName":["Fitzpatrick, S"],"firstname":["Sulu"],"surname":["Fitzpatrick"],"displayName":["S.Fitzpatrick"],"playerId":[80305]},{"shortDisplayName":["Burley, K"],"firstname":["Kate"],"surname":["Burley"],"displayName":["K.Burley"],"playerId":[80808]},{"shortDisplayName":["Ioane, F"],"firstname":["Fa'amu"],"surname":["Ioane"],"displayName":["F.Ioane"],"playerId":[998998]},{"shortDisplayName":["Taane"],"firstname":["Jess"],"surname":["Taane"],"displayName":["J.Taane"],"playerId":[80229]}]},"playerPeriodStats":{"player":[{"rebounds":[0],"penalties":[1],"gain":[0],"offensiveRebounds":[0],"possessions":[5],"goalMisses":[0],"blocked":[0],"passes":[1],"goalAssists":[0],"tossUpWin":[0],"disposals":[4],"centrePassReceives":[2],"obstructionPenalties":[0],"feeds":[1],"playerId":[80028],"goals":[2],"offsides":[0],"badPasses":[0],"period":[1],"defensiveRebounds":[0],"breaks":[0],"blocks":[0],"badHands":[0],"missedGoalTurnover":[0],"squadId":[802],"startingPositionCode":["GA"],"goalAttempts":[2],"deflections":[0],"contactPenalties":[1],"quartersPlayed":[1],"minutesPlayed":[12],"turnovers":[3],"pickups":[0],"currentPositionCode":["I"],"intercepts":[0]},{"rebounds":[0],"penalties":[0],"gain":[0],"offensiveRebounds":[0],"possessions":[3],"goalMisses":[0],"blocked":[0],"passes":[0],"goalAssists":[0],"tossUpWin":[0],"disposals":[1],"centrePassReceives":[2],"obstructionPenalties":[0],"feeds":[0],"playerId":[80028],"goals":[1],"offsides":[0],"badPasses":[0],"period":[2],"defensiveRebounds":[0],"breaks":[0],"blocks":[0],"badHands":[0],"missedGoalTurnover":[0],"squadId":[802],"startingPositionCode":["I"],"goalAttempts":[1],"deflections":[0],"contactPenalties":[0],"quartersPlayed":[1],"minutesPlayed":[5],"turnovers":[0],"pickups":[0],"currentPositionCode":["GA"],"intercepts":[0]},{"rebounds":[0],"penalties":[1],"gain":[0],"offensiveRebounds":[0],"possessions":[6],"goalMisses":[0],"blocked":[0],"passes":[4],"goalAssists":[1],"tossUpWin":[0],"disposals":[6],"centrePassReceives":[4],"obstructionPenalties":[0],"feeds":[4],"playerId":[80028],"goals":[1],"offsides":[0],"badPasses":[0],"period":[3],"defensiveRebounds":[0],"breaks":[0],"blocks":[0],"badHands":[1],"missedGoalTurnover":[0],"squadId":[802],"startingPositionCode":["GA"],"goalAttempts":[1],"deflections":[0],"contactPenalties":[1],"quartersPlayed":[1],"minutesPlayed":[15],"turnovers":[2],"pickups":[0],"currentPositionCode":["GA"],"intercepts":[0]},{"rebounds":[0],"penalties":[0],"gain":[0],"offensiveRebounds":[0],"possessions":[11],"goalMisses":[2],"blocked":[0],"passes":[3],"goalAssists":[3],"tossUpWin":[0],"disposals":[11],"centrePassReceives":[3],"obstructionPenalties":[0],"feeds":[3],"playerId":[80028],"goals":[6],"offsides":[0],"badPasses":[0],"period":[4],"defensiveRebounds":[0],"breaks":[0],"blocks":[0],"badHands":[0],"missedGoalTurnover":[0],"squadId":[802],"startingPositionCode":["GA"],"goalAttempts":[8],"deflections":[0],"contactPenalties":[0],"quartersPlayed":[1],"minutesPlayed":[15],"turnovers":[1],"pickups":[0],"currentPositionCode":["GA"],"intercepts":[0]},{"rebounds":[0],"penalties":[5],"gain":[0],"offensiveRebounds":[0],"possessions":[5],"goalMisses":[0],"blocked":[0],"passes":[0],"goalAssists":[0],"tossUpWin":[0],"disposals":[0],"centrePassReceives":[3],"obstructionPenalties":[1],"feeds":[0],"playerId":[80223],"goals":[0],"offsides":[0],"badPasses":[1],"period":[1],"defensiveRebounds":[0],"breaks":[0],"blocks":[0],"badHands":[0],"missedGoalTurnover":[0],"squadId":[802],"startingPositionCode":["WD"],"goalAttempts":[0],"deflections":[0],"contactPenalties":[4],"quartersPlayed":[1],"minutesPlayed":[15],"turnovers":[1],"pickups":[1],"currentPositionCode":["WD"],"intercepts":[0]},{"rebounds":[0],"penalties":[1],"gain":[1],"offensiveRebounds":[0],"possessions":[3],"goalMisses":[0],"blocked":[0],"passes":[2],"goalAssists":[0],"tossUpWin":[0],"disposals":[2],"centrePassReceives":[2],"obstructionPenalties":[0],"feeds":[2],"playerId":[80223],"goals":[0],"offsides":[0],"badPasses":[0],"period":[2],"defensiveRebounds":[0],"breaks":[0],"blocks":[0],"badHands":[1],"missedGoalTurnover":[0],"squadId":[802],"startingPositionCode":["WD"],"goalAttempts":[0],"deflections":[0],"contactPenalties":[1],"quartersPlayed":[1],"minutesPlayed":[15],"turnovers":[1],"pickups":[0],"currentPositionCode":["WD"],"intercepts":[1]},{"rebounds":[0],"penalties":[0],"gain":[0],"offensiveRebounds":[0],"possessions":[2],"goalMisses":[0],"blocked":[0],"passes":[0],"goalAssists":[0],"tossUpWin":[0],"disposals":[0],"centrePassReceives":[1],"obstructionPenalties":[0],"feeds":[0],"playerId":[80223],"goals":[0],"offsides":[0],"badPasses":[0],"period":[3],"defensiveRebounds":[0],"breaks":[0],"blocks":[0],"badHands":[0],"missedGoalTurnover":[0],"squadId":[802],"startingPositionCode":["WD"],"goalAttempts":[0],"deflections":[0],"contactPenalties":[0],"quartersPlayed":[1],"minutesPlayed":[15],"turnovers":[0],"pickups":[1],"currentPositionCode":["WD"],"intercepts":[0]},{"rebounds":[0],"penalties":[1],"gain":[0],"offensiveRebounds":[0],"possessions":[0],"goalMisses":[0],"blocked":[0],"passes":[0],"goalAssists":[0],"tossUpWin":[0],"disposals":[0],"centrePassReceives":[0],"obstructionPenalties":[0],"feeds":[0],"playerId":[80223],"goals":[0],"offsides":[1],"badPasses":[0],"period":[4],"defensiveRebounds":[0],"breaks":[1],"blocks":[0],"badHands":[0],"missedGoalTurnover":[0],"squadId":[802],"startingPositionCode":["WD"],"goalAttempts":[0],"deflections":[1],"contactPenalties":[1],"quartersPlayed":[1],"minutesPlayed":[15],"turnovers":[0],"pickups":[0],"currentPositionCode":["WD"],"intercepts":[0]},{"rebounds":[1],"penalties":[2],"gain":[0],"offensiveRebounds":[1],"possessions":[11],"goalMisses":[3],"blocked":[0],"passes":[1],"goalAssists":[1],"tossUpWin":[0],"disposals":[10],"centrePassReceives":[0],"obstructionPenalties":[1],"feeds":[1],"playerId":[80469],"goals":[6],"offsides":[0],"badPasses":[0],"period":[1],"defensiveRebounds":[0],"breaks":[0],"blocks":[0],"badHands":[0],"missedGoalTurnover":[0],"squadId":[802],"startingPositionCode":["GS"],"goalAttempts":[9],"deflections":[0],"contactPenalties":[1],"quartersPlayed":[1],"minutesPlayed":[15],"turnovers":[0],"pickups":[1],"currentPositionCode":["GS"],"intercepts":[0]},{"rebounds":[1],"penalties":[1],"gain":[0],"offensiveRebounds":[1],"possessions":[4],"goalMisses":[0],"blocked":[0],"passes":[1],"goalAssists":[1],"tossUpWin":[0],"disposals":[4],"centrePassReceives":[0],"obstructionPenalties":[0],"feeds":[1],"playerId":[80469],"goals":[2],"offsides":[0],"badPasses":[0],"period":[2],"defensiveRebounds":[0],"breaks":[0],"blocks":[0],"badHands":[1],"missedGoalTurnover":[0],"squadId":[802],"startingPositionCode":["GS"],"goalAttempts":[2],"deflections":[0],"contactPenalties":[1],"quartersPlayed":[1],"minutesPlayed":[11],"turnovers":[2],"pickups":[0],"currentPositionCode":["I"],"intercepts":[0]},{"rebounds":[0],"penalties":[0],"gain":[0],"offensiveRebounds":[0],"possessions":[0],"goalMisses":[0],"blocked":[0],"passes":[0],"goalAssists":[0],"tossUpWin":[0],"disposals":[0],"centrePassReceives":[0],"obstructionPenalties":[0],"feeds":[0],"playerId":[80469],"goals":[0],"offsides":[0],"badPasses":[0],"period":[3],"defensiveRebounds":[0],"breaks":[0],"blocks":[0],"badHands":[0],"missedGoalTurnover":[0],"squadId":[802],"startingPositionCode":["I"],"goalAttempts":[0],"deflections":[0],"contactPenalties":[0],"quartersPlayed":[0],"minutesPlayed":[0],"turnovers":[0],"pickups":[0],"currentPositionCode":["I"],"intercepts":[0]},{"rebounds":[0],"penalties":[0],"gain":[0],"offensiveRebounds":[0],"possessions":[0],"goalMisses":[0],"blocked":[0],"passes":[0],"goalAssists":[0],"tossUpWin":[0],"disposals":[0],"centrePassReceives":[0],"obstructionPenalties":[0],"feeds":[0],"playerId":[80469],"goals":[0],"offsides":[0],"badPasses":[0],"period":[4],"defensiveRebounds":[0],"breaks":[0],"blocks":[0],"badHands":[0],"missedGoalTurnover":[0],"squadId":[802],"startingPositionCode":["I"],"goalAttempts":[0],"deflections":[0],"contactPenalties":[0],"quartersPlayed":[0],"minutesPlayed":[0],"turnovers":[0],"pickups":[0],"currentPositionCode":["I"],"intercepts":[0]},{"rebounds":[3],"penalties":[6],"gain":[4],"offensiveRebounds":[0],"possessions":[3],"goalMisses":[0],"blocked":[0],"passes":[0],"goalAssists":[0],"tossUpWin":[0],"disposals":[0],"centrePassReceives":[0],"obstructionPenalties":[1],"feeds":[0],"playerId":[80524],"goals":[0],"offsides":[0],"badPasses":[0],"period":[1],"defensiveRebounds":[3],"breaks":[0],"blocks":[0],"badHands":[0],"missedGoalTurnover":[0],"squadId":[802],"startingPositionCode":["GD"],"goalAttempts":[0],"deflections":[2],"contactPenalties":[5],"quartersPlayed":[1],"minutesPlayed":[15],"turnovers":[0],"pickups":[0],"currentPositionCode":["GD"],"intercepts":[0]},{"rebounds":[1],"penalties":[1],"gain":[1],"offensiveRebounds":[0],"possessions":[3],"goalMisses":[0],"blocked":[0],"passes":[0],"goalAssists":[0],"tossUpWin":[0],"disposals":[0],"centrePassReceives":[2],"obstructionPenalties":[0],"feeds":[0],"playerId":[80524],"goals":[0],"offsides":[0],"badPasses":[0],"period":[2],"defensiveRebounds":[1],"breaks":[0],"blocks":[0],"badHands":[0],"missedGoalTurnover":[0],"squadId":[802],"startingPositionCode":["GD"],"goalAttempts":[0],"deflections":[0],"contactPenalties":[1],"quartersPlayed":[1],"minutesPlayed":[15],"turnovers":[0],"pickups":[0],"currentPositionCode":["GD"],"intercepts":[0]},{"rebounds":[0],"penalties":[6],"gain":[0],"offensiveRebounds":[0],"possessions":[2],"goalMisses":[0],"blocked":[0],"passes":[0],"goalAssists":[0],"tossUpWin":[0],"disposals":[0],"centrePassReceives":[0],"obstructionPenalties":[1],"feeds":[0],"playerId":[80524],"goals":[0],"offsides":[0],"badPasses":[0],"period":[3],"defensiveRebounds":[0],"breaks":[0],"blocks":[0],"badHands":[0],"missedGoalTurnover":[0],"squadId":[802],"startingPositionCode":["GD"],"goalAttempts":[0],"deflections":[1],"contactPenalties":[5],"quartersPlayed":[1],"minutesPlayed":[15],"turnovers":[0],"pickups":[1],"currentPositionCode":["GD"],"intercepts":[0]},{"rebounds":[0],"penalties":[4],"gain":[0],"offensiveRebounds":[0],"possessions":[3],"goalMisses":[0],"blocked":[0],"passes":[0],"goalAssists":[0],"tossUpWin":[0],"disposals":[1],"centrePassReceives":[2],"obstructionPenalties":[0],"feeds":[0],"playerId":[80524],"goals":[0],"offsides":[0],"badPasses":[0],"period":[4],"defensiveRebounds":[0],"breaks":[0],"blocks":[0],"badHands":[0],"missedGoalTurnover":[0],"squadId":[802],"startingPositionCode":["GD"],"goalAttempts":[0],"deflections":[0],"contactPenalties":[4],"quartersPlayed":[1],"minutesPlayed":[15],"turnovers":[0],"pickups":[0],"currentPositionCode":["GD"],"intercepts":[0]},{"rebounds":[0],"penalties":[4],"gain":[0],"offensiveRebounds":[0],"possessions":[0],"goalMisses":[0],"blocked":[0],"passes":[9],"goalAssists":[3],"tossUpWin":[0],"disposals":[9],"centrePassReceives":[0],"obstructionPenalties":[2],"feeds":[9],"playerId":[80526],"goals":[0],"offsides":[1],"badPasses":[0],"period":[1],"defensiveRebounds":[0],"breaks":[0],"blocks":[0],"badHands":[0],"missedGoalTurnover":[0],"squadId":[802],"startingPositionCode":["C"],"goalAttempts":[0],"deflections":[0],"contactPenalties":[2],"quartersPlayed":[1],"minutesPlayed":[15],"turnovers":[1],"pickups":[0],"currentPositionCode":["C"],"intercepts":[0]},{"rebounds":[0],"penalties":[0],"gain":[0],"offensiveRebounds":[0],"possessions":[2],"goalMisses":[0],"blocked":[0],"passes":[7],"goalAssists":[0],"tossUpWin":[0],"disposals":[7],"centrePassReceives":[0],"obstructionPenalties":[0],"feeds":[7],"playerId":[80526],"goals":[0],"offsides":[0],"badPasses":[0],"period":[2],"defensiveRebounds":[0],"breaks":[0],"blocks":[0],"badHands":[0],"missedGoalTurnover":[0],"squadId":[802],"startingPositionCode":["C"],"goalAttempts":[0],"deflections":[0],"contactPenalties":[0],"quartersPlayed":[1],"minutesPlayed":[15],"turnovers":[0],"pickups":[1],"currentPositionCode":["C"],"intercepts":[0]},{"rebounds":[0],"penalties":[2],"gain":[1],"offensiveRebounds":[0],"possessions":[1],"goalMisses":[0],"blocked":[0],"passes":[12],"goalAssists":[2],"tossUpWin":[0],"disposals":[12],"centrePassReceives":[0],"obstructionPenalties":[0],"feeds":[12],"playerId":[80526],"goals":[0],"offsides":[0],"badPasses":[1],"period":[3],"defensiveRebounds":[0],"breaks":[0],"blocks":[0],"badHands":[0],"missedGoalTurnover":[0],"squadId":[802],"startingPositionCode":["C"],"goalAttempts":[0],"deflections":[0],"contactPenalties":[2],"quartersPlayed":[1],"minutesPlayed":[15],"turnovers":[1],"pickups":[0],"currentPositionCode":["C"],"intercepts":[1]},{"rebounds":[0],"penalties":[4],"gain":[0],"offensiveRebounds":[0],"possessions":[0],"goalMisses":[0],"blocked":[0],"passes":[8],"goalAssists":[3],"tossUpWin":[0],"disposals":[8],"centrePassReceives":[0],"obstructionPenalties":[1],"feeds":[8],"playerId":[80526],"goals":[0],"offsides":[0],"badPasses":[1],"period":[4],"defensiveRebounds":[0],"breaks":[0],"blocks":[0],"badHands":[0],"missedGoalTurnover":[0],"squadId":[802],"startingPositionCode":["C"],"goalAttempts":[0],"deflections":[0],"contactPenalties":[3],"quartersPlayed":[1],"minutesPlayed":[12],"turnovers":[1],"pickups":[0],"currentPositionCode":["I"],"intercepts":[0]},{"rebounds":[1],"penalties":[0],"gain":[0],"offensiveRebounds":[1],"possessions":[5],"goalMisses":[1],"blocked":[0],"passes":[2],"goalAssists":[1],"tossUpWin":[0],"disposals":[5],"centrePassReceives":[1],"obstructionPenalties":[0],"feeds":[2],"playerId":[80532],"goals":[2],"offsides":[0],"badPasses":[0],"period":[1],"defensiveRebounds":[0],"breaks":[0],"blocks":[0],"badHands":[0],"missedGoalTurnover":[0],"squadId":[802],"startingPositionCode":["I"],"goalAttempts":[3],"deflections":[0],"contactPenalties":[0],"quartersPlayed":[1],"minutesPlayed":[4],"turnovers":[0],"pickups":[0],"currentPositionCode":["GA"],"intercepts":[0]},{"rebounds":[0],"penalties":[1],"gain":[0],"offensiveRebounds":[0],"possessions":[14],"goalMisses":[2],"blocked":[0],"passes":[2],"goalAssists":[0],"tossUpWin":[0],"disposals":[14],"centrePassReceives":[2],"obstructionPenalties":[0],"feeds":[2],"playerId":[80532],"goals":[9],"offsides":[0],"badPasses":[2],"period":[2],"defensiveRebounds":[0],"breaks":[0],"blocks":[0],"badHands":[1],"missedGoalTurnover":[0],"squadId":[802],"startingPositionCode":["GA"],"goalAttempts":[11],"deflections":[0],"contactPenalties":[1],"quartersPlayed":[1],"minutesPlayed":[15],"turnovers":[3],"pickups":[0],"currentPositionCode":["GS"],"intercepts":[0]},{"rebounds":[0],"penalties":[1],"gain":[0],"offensiveRebounds":[0],"possessions":[12],"goalMisses":[4],"blocked":[0],"passes":[0],"goalAssists":[0],"tossUpWin":[0],"disposals":[12],"centrePassReceives":[0],"obstructionPenalties":[0],"feeds":[0],"playerId":[80532],"goals":[8],"offsides":[0],"badPasses":[0],"period":[3],"defensiveRebounds":[0],"breaks":[0],"blocks":[0],"badHands":[0],"missedGoalTurnover":[0],"squadId":[802],"startingPositionCode":["GS"],"goalAttempts":[12],"deflections":[0],"contactPenalties":[1],"quartersPlayed":[1],"minutesPlayed":[15],"turnovers":[4],"pickups":[0],"currentPositionCode":["GS"],"intercepts":[0]},{"rebounds":[0],"penalties":[2],"gain":[0],"offensiveRebounds":[0],"possessions":[9],"goalMisses":[2],"blocked":[0],"passes":[2],"goalAssists":[1],"tossUpWin":[0],"disposals":[11],"centrePassReceives":[0],"obstructionPenalties":[0],"feeds":[2],"playerId":[80532],"goals":[7],"offsides":[0],"badPasses":[0],"period":[4],"defensiveRebounds":[0],"breaks":[0],"blocks":[0],"badHands":[0],"missedGoalTurnover":[0],"squadId":[802],"startingPositionCode":["GS"],"goalAttempts":[9],"deflections":[0],"contactPenalties":[2],"quartersPlayed":[1],"minutesPlayed":[15],"turnovers":[4],"pickups":[0],"currentPositionCode":["GS"],"intercepts":[0]},{"rebounds":[0],"penalties":[4],"gain":[1],"offensiveRebounds":[0],"possessions":[1],"goalMisses":[0],"blocked":[0],"passes":[0],"goalAssists":[0],"tossUpWin":[0],"disposals":[0],"centrePassReceives":[0],"obstructionPenalties":[3],"feeds":[0],"playerId":[80604],"goals":[0],"offsides":[0],"badPasses":[0],"period":[1],"defensiveRebounds":[0],"breaks":[0],"blocks":[0],"badHands":[0],"missedGoalTurnover":[0],"squadId":[802],"startingPositionCode":["GK"],"goalAttempts":[0],"deflections":[3],"contactPenalties":[1],"quartersPlayed":[1],"minutesPlayed":[15],"turnovers":[0],"pickups":[0],"currentPositionCode":["GK"],"intercepts":[1]},{"rebounds":[1],"penalties":[1],"gain":[5],"offensiveRebounds":[0],"possessions":[7],"goalMisses":[0],"blocked":[0],"passes":[0],"goalAssists":[0],"tossUpWin":[0],"disposals":[3],"centrePassReceives":[0],"obstructionPenalties":[0],"feeds":[0],"playerId":[80604],"goals":[0],"offsides":[0],"badPasses":[0],"period":[2],"defensiveRebounds":[1],"breaks":[0],"blocks":[0],"badHands":[0],"missedGoalTurnover":[0],"squadId":[802],"startingPositionCode":["GK"],"goalAttempts":[0],"deflections":[2],"contactPenalties":[1],"quartersPlayed":[1],"minutesPlayed":[15],"turnovers":[0],"pickups":[0],"currentPositionCode":["GK"],"intercepts":[3]},{"rebounds":[0],"penalties":[2],"gain":[5],"offensiveRebounds":[0],"possessions":[4],"goalMisses":[0],"blocked":[0],"passes":[0],"goalAssists":[0],"tossUpWin":[0],"disposals":[1],"centrePassReceives":[0],"obstructionPenalties":[1],"feeds":[0],"playerId":[80604],"goals":[0],"offsides":[0],"badPasses":[0],"period":[3],"defensiveRebounds":[0],"breaks":[0],"blocks":[0],"badHands":[0],"missedGoalTurnover":[0],"squadId":[802],"startingPositionCode":["GK"],"goalAttempts":[0],"deflections":[1],"contactPenalties":[1],"quartersPlayed":[1],"minutesPlayed":[15],"turnovers":[0],"pickups":[0],"currentPositionCode":["GK"],"intercepts":[3]},{"rebounds":[1],"penalties":[4],"gain":[1],"offensiveRebounds":[0],"possessions":[5],"goalMisses":[0],"blocked":[0],"passes":[0],"goalAssists":[0],"tossUpWin":[0],"disposals":[3],"centrePassReceives":[0],"obstructionPenalties":[0],"feeds":[0],"playerId":[80604],"goals":[0],"offsides":[0],"badPasses":[0],"period":[4],"defensiveRebounds":[1],"breaks":[0],"blocks":[0],"badHands":[0],"missedGoalTurnover":[0],"squadId":[802],"startingPositionCode":["GK"],"goalAttempts":[0],"deflections":[2],"contactPenalties":[4],"quartersPlayed":[1],"minutesPlayed":[15],"turnovers":[0],"pickups":[1],"currentPositionCode":["GK"],"intercepts":[0]},{"rebounds":[0],"penalties":[1],"gain":[0],"offensiveRebounds":[0],"possessions":[6],"goalMisses":[0],"blocked":[0],"passes":[8],"goalAssists":[1],"tossUpWin":[0],"disposals":[9],"centrePassReceives":[5],"obstructionPenalties":[1],"feeds":[8],"playerId":[80699],"goals":[0],"offsides":[0],"badPasses":[0],"period":[1],"defensiveRebounds":[0],"breaks":[0],"blocks":[0],"badHands":[0],"missedGoalTurnover":[0],"squadId":[802],"startingPositionCode":["WA"],"goalAttempts":[0],"deflections":[0],"contactPenalties":[0],"quartersPlayed":[1],"minutesPlayed":[15],"turnovers":[0],"pickups":[0],"currentPositionCode":["WA"],"intercepts":[0]},{"rebounds":[0],"penalties":[0],"gain":[0],"offensiveRebounds":[0],"possessions":[5],"goalMisses":[0],"blocked":[0],"passes":[11],"goalAssists":[8],"tossUpWin":[0],"disposals":[12],"centrePassReceives":[4],"obstructionPenalties":[0],"feeds":[11],"playerId":[80699],"goals":[0],"offsides":[0],"badPasses":[2],"period":[2],"defensiveRebounds":[0],"breaks":[0],"blocks":[0],"badHands":[1],"missedGoalTurnover":[0],"squadId":[802],"startingPositionCode":["WA"],"goalAttempts":[0],"deflections":[0],"contactPenalties":[0],"quartersPlayed":[1],"minutesPlayed":[15],"turnovers":[3],"pickups":[0],"currentPositionCode":["WA"],"intercepts":[0]},{"rebounds":[0],"penalties":[1],"gain":[0],"offensiveRebounds":[0],"possessions":[6],"goalMisses":[0],"blocked":[0],"passes":[11],"goalAssists":[6],"tossUpWin":[0],"disposals":[12],"centrePassReceives":[5],"obstructionPenalties":[0],"feeds":[11],"playerId":[80699],"goals":[0],"offsides":[0],"badPasses":[0],"period":[3],"defensiveRebounds":[0],"breaks":[0],"blocks":[0],"badHands":[0],"missedGoalTurnover":[0],"squadId":[802],"startingPositionCode":["WA"],"goalAttempts":[0],"deflections":[0],"contactPenalties":[1],"quartersPlayed":[1],"minutesPlayed":[15],"turnovers":[0],"pickups":[0],"currentPositionCode":["WA"],"intercepts":[0]},{"rebounds":[0],"penalties":[4],"gain":[0],"offensiveRebounds":[0],"possessions":[6],"goalMisses":[0],"blocked":[0],"passes":[10],"goalAssists":[3],"tossUpWin":[0],"disposals":[10],"centrePassReceives":[6],"obstructionPenalties":[1],"feeds":[10],"playerId":[80699],"goals":[0],"offsides":[0],"badPasses":[0],"period":[4],"defensiveRebounds":[0],"breaks":[0],"blocks":[0],"badHands":[0],"missedGoalTurnover":[0],"squadId":[802],"startingPositionCode":["WA"],"goalAttempts":[0],"deflections":[0],"contactPenalties":[3],"quartersPlayed":[1],"minutesPlayed":[15],"turnovers":[0],"pickups":[0],"currentPositionCode":["WA"],"intercepts":[0]},{"rebounds":[0],"penalties":[0],"gain":[0],"offensiveRebounds":[0],"possessions":[0],"goalMisses":[0],"blocked":[0],"passes":[0],"goalAssists":[0],"tossUpWin":[0],"disposals":[0],"centrePassReceives":[0],"obstructionPenalties":[0],"feeds":[0],"playerId":[997432],"goals":[0],"offsides":[0],"badPasses":[0],"period":[1],"defensiveRebounds":[0],"breaks":[0],"blocks":[0],"badHands":[0],"missedGoalTurnover":[0],"squadId":[802],"startingPositionCode":["I"],"goalAttempts":[0],"deflections":[0],"contactPenalties":[0],"quartersPlayed":[0],"minutesPlayed":[0],"turnovers":[0],"pickups":[0],"currentPositionCode":["I"],"intercepts":[0]},{"rebounds":[0],"penalties":[0],"gain":[0],"offensiveRebounds":[0],"possessions":[0],"goalMisses":[0],"blocked":[0],"passes":[0],"goalAssists":[0],"tossUpWin":[0],"disposals":[0],"centrePassReceives":[0],"obstructionPenalties":[0],"feeds":[0],"playerId":[997432],"goals":[0],"offsides":[0],"badPasses":[0],"period":[2],"defensiveRebounds":[0],"breaks":[0],"blocks":[0],"badHands":[0],"missedGoalTurnover":[0],"squadId":[802],"startingPositionCode":["I"],"goalAttempts":[0],"deflections":[0],"contactPenalties":[0],"quartersPlayed":[0],"minutesPlayed":[0],"turnovers":[0],"pickups":[0],"currentPositionCode":["I"],"intercepts":[0]},{"rebounds":[0],"penalties":[0],"gain":[0],"offensiveRebounds":[0],"possessions":[0],"goalMisses":[0],"blocked":[0],"passes":[0],"goalAssists":[0],"tossUpWin":[0],"disposals":[0],"centrePassReceives":[0],"obstructionPenalties":[0],"feeds":[0],"playerId":[997432],"goals":[0],"offsides":[0],"badPasses":[0],"period":[3],"defensiveRebounds":[0],"breaks":[0],"blocks":[0],"badHands":[0],"missedGoalTurnover":[0],"squadId":[802],"startingPositionCode":["I"],"goalAttempts":[0],"deflections":[0],"contactPenalties":[0],"quartersPlayed":[0],"minutesPlayed":[0],"turnovers":[0],"pickups":[0],"currentPositionCode":["I"],"intercepts":[0]},{"rebounds":[0],"penalties":[1],"gain":[0],"offensiveRebounds":[0],"possessions":[0],"goalMisses":[0],"blocked":[0],"passes":[3],"goalAssists":[0],"tossUpWin":[0],"disposals":[3],"centrePassReceives":[0],"obstructionPenalties":[1],"feeds":[3],"playerId":[997432],"goals":[0],"offsides":[0],"badPasses":[0],"period":[4],"defensiveRebounds":[0],"breaks":[0],"blocks":[0],"badHands":[0],"missedGoalTurnover":[0],"squadId":[802],"startingPositionCode":["I"],"goalAttempts":[0],"deflections":[0],"contactPenalties":[0],"quartersPlayed":[1],"minutesPlayed":[4],"turnovers":[0],"pickups":[0],"currentPositionCode":["C"],"intercepts":[0]},{"rebounds":[0],"penalties":[0],"gain":[0],"offensiveRebounds":[0],"possessions":[0],"goalMisses":[0],"blocked":[0],"passes":[0],"goalAssists":[0],"tossUpWin":[0],"disposals":[0],"centrePassReceives":[0],"obstructionPenalties":[0],"feeds":[0],"playerId":[999790],"goals":[0],"offsides":[0],"badPasses":[0],"period":[1],"defensiveRebounds":[0],"breaks":[0],"blocks":[0],"badHands":[0],"missedGoalTurnover":[0],"squadId":[802],"startingPositionCode":["I"],"goalAttempts":[0],"deflections":[0],"contactPenalties":[0],"quartersPlayed":[0],"minutesPlayed":[0],"turnovers":[0],"pickups":[0],"currentPositionCode":["I"],"intercepts":[0]},{"rebounds":[0],"penalties":[0],"gain":[0],"offensiveRebounds":[0],"possessions":[0],"goalMisses":[0],"blocked":[0],"passes":[0],"goalAssists":[0],"tossUpWin":[0],"disposals":[0],"centrePassReceives":[0],"obstructionPenalties":[0],"feeds":[0],"playerId":[999790],"goals":[0],"offsides":[0],"badPasses":[0],"period":[2],"defensiveRebounds":[0],"breaks":[0],"blocks":[0],"badHands":[0],"missedGoalTurnover":[0],"squadId":[802],"startingPositionCode":["I"],"goalAttempts":[0],"deflections":[0],"contactPenalties":[0],"quartersPlayed":[0],"minutesPlayed":[0],"turnovers":[0],"pickups":[0],"currentPositionCode":["I"],"intercepts":[0]},{"rebounds":[0],"penalties":[0],"gain":[0],"offensiveRebounds":[0],"possessions":[0],"goalMisses":[0],"blocked":[0],"passes":[0],"goalAssists":[0],"tossUpWin":[0],"disposals":[0],"centrePassReceives":[0],"obstructionPenalties":[0],"feeds":[0],"playerId":[999790],"goals":[0],"offsides":[0],"badPasses":[0],"period":[3],"defensiveRebounds":[0],"breaks":[0],"blocks":[0],"badHands":[0],"missedGoalTurnover":[0],"squadId":[802],"startingPositionCode":["I"],"goalAttempts":[0],"deflections":[0],"contactPenalties":[0],"quartersPlayed":[0],"minutesPlayed":[0],"turnovers":[0],"pickups":[0],"currentPositionCode":["I"],"intercepts":[0]},{"rebounds":[0],"penalties":[0],"gain":[0],"offensiveRebounds":[0],"possessions":[0],"goalMisses":[0],"blocked":[0],"passes":[0],"goalAssists":[0],"tossUpWin":[0],"disposals":[0],"centrePassReceives":[0],"obstructionPenalties":[0],"feeds":[0],"playerId":[999790],"goals":[0],"offsides":[0],"badPasses":[0],"period":[4],"defensiveRebounds":[0],"breaks":[0],"blocks":[0],"badHands":[0],"missedGoalTurnover":[0],"squadId":[802],"startingPositionCode":["I"],"goalAttempts":[0],"deflections":[0],"contactPenalties":[0],"quartersPlayed":[0],"minutesPlayed":[0],"turnovers":[0],"pickups":[0],"currentPositionCode":["I"],"intercepts":[0]},{"rebounds":[0],"penalties":[2],"gain":[0],"offensiveRebounds":[0],"possessions":[0],"goalMisses":[0],"blocked":[0],"passes":[0],"goalAssists":[0],"tossUpWin":[0],"disposals":[0],"centrePassReceives":[0],"obstructionPenalties":[0],"feeds":[0],"playerId":[80057],"goals":[0],"offsides":[0],"badPasses":[0],"period":[1],"defensiveRebounds":[0],"breaks":[0],"blocks":[0],"badHands":[0],"missedGoalTurnover":[0],"squadId":[8120],"startingPositionCode":["GD"],"goalAttempts":[0],"deflections":[3],"contactPenalties":[2],"quartersPlayed":[1],"minutesPlayed":[15],"turnovers":[0],"pickups":[0],"currentPositionCode":["GD"],"intercepts":[0]},{"rebounds":[0],"penalties":[3],"gain":[2],"offensiveRebounds":[0],"possessions":[7],"goalMisses":[0],"blocked":[0],"passes":[0],"goalAssists":[0],"tossUpWin":[0],"disposals":[1],"centrePassReceives":[0],"obstructionPenalties":[0],"feeds":[0],"playerId":[80057],"goals":[0],"offsides":[0],"badPasses":[0],"period":[2],"defensiveRebounds":[0],"breaks":[0],"blocks":[0],"badHands":[0],"missedGoalTurnover":[0],"squadId":[8120],"startingPositionCode":["GD"],"goalAttempts":[0],"deflections":[0],"contactPenalties":[3],"quartersPlayed":[1],"minutesPlayed":[15],"turnovers":[0],"pickups":[2],"currentPositionCode":["GD"],"intercepts":[2]},{"rebounds":[1],"penalties":[1],"gain":[2],"offensiveRebounds":[0],"possessions":[4],"goalMisses":[0],"blocked":[0],"passes":[1],"goalAssists":[0],"tossUpWin":[0],"disposals":[1],"centrePassReceives":[0],"obstructionPenalties":[0],"feeds":[1],"playerId":[80057],"goals":[0],"offsides":[0],"badPasses":[0],"period":[3],"defensiveRebounds":[1],"breaks":[0],"blocks":[0],"badHands":[0],"missedGoalTurnover":[0],"squadId":[8120],"startingPositionCode":["GD"],"goalAttempts":[0],"deflections":[1],"contactPenalties":[1],"quartersPlayed":[1],"minutesPlayed":[15],"turnovers":[0],"pickups":[1],"currentPositionCode":["GD"],"intercepts":[1]},{"rebounds":[2],"penalties":[2],"gain":[2],"offensiveRebounds":[0],"possessions":[4],"goalMisses":[0],"blocked":[0],"passes":[1],"goalAssists":[1],"tossUpWin":[0],"disposals":[2],"centrePassReceives":[1],"obstructionPenalties":[0],"feeds":[1],"playerId":[80057],"goals":[0],"offsides":[0],"badPasses":[0],"period":[4],"defensiveRebounds":[2],"breaks":[0],"blocks":[0],"badHands":[0],"missedGoalTurnover":[0],"squadId":[8120],"startingPositionCode":["GD"],"goalAttempts":[0],"deflections":[0],"contactPenalties":[2],"quartersPlayed":[1],"minutesPlayed":[15],"turnovers":[0],"pickups":[0],"currentPositionCode":["GD"],"intercepts":[0]},{"rebounds":[0],"penalties":[1],"gain":[0],"offensiveRebounds":[0],"possessions":[1],"goalMisses":[0],"blocked":[0],"passes":[6],"goalAssists":[2],"tossUpWin":[0],"disposals":[6],"centrePassReceives":[0],"obstructionPenalties":[0],"feeds":[6],"playerId":[80182],"goals":[0],"offsides":[0],"badPasses":[0],"period":[1],"defensiveRebounds":[0],"breaks":[0],"blocks":[0],"badHands":[0],"missedGoalTurnover":[0],"squadId":[8120],"startingPositionCode":["C"],"goalAttempts":[0],"deflections":[0],"contactPenalties":[1],"quartersPlayed":[1],"minutesPlayed":[15],"turnovers":[0],"pickups":[1],"currentPositionCode":["C"],"intercepts":[0]},{"rebounds":[0],"penalties":[2],"gain":[0],"offensiveRebounds":[0],"possessions":[1],"goalMisses":[0],"blocked":[0],"passes":[5],"goalAssists":[2],"tossUpWin":[0],"disposals":[5],"centrePassReceives":[0],"obstructionPenalties":[1],"feeds":[5],"playerId":[80182],"goals":[0],"offsides":[0],"badPasses":[0],"period":[2],"defensiveRebounds":[0],"breaks":[0],"blocks":[0],"badHands":[1],"missedGoalTurnover":[0],"squadId":[8120],"startingPositionCode":["C"],"goalAttempts":[0],"deflections":[0],"contactPenalties":[1],"quartersPlayed":[1],"minutesPlayed":[15],"turnovers":[1],"pickups":[1],"currentPositionCode":["C"],"intercepts":[0]},{"rebounds":[0],"penalties":[0],"gain":[1],"offensiveRebounds":[0],"possessions":[5],"goalMisses":[0],"blocked":[0],"passes":[9],"goalAssists":[3],"tossUpWin":[0],"disposals":[10],"centrePassReceives":[4],"obstructionPenalties":[0],"feeds":[9],"playerId":[80182],"goals":[0],"offsides":[0],"badPasses":[0],"period":[3],"defensiveRebounds":[0],"breaks":[0],"blocks":[0],"badHands":[0],"missedGoalTurnover":[0],"squadId":[8120],"startingPositionCode":["C"],"goalAttempts":[0],"deflections":[1],"contactPenalties":[0],"quartersPlayed":[1],"minutesPlayed":[15],"turnovers":[0],"pickups":[0],"currentPositionCode":["WA"],"intercepts":[0]},{"rebounds":[0],"penalties":[0],"gain":[0],"offensiveRebounds":[0],"possessions":[4],"goalMisses":[0],"blocked":[0],"passes":[5],"goalAssists":[3],"tossUpWin":[0],"disposals":[5],"centrePassReceives":[4],"obstructionPenalties":[0],"feeds":[5],"playerId":[80182],"goals":[0],"offsides":[0],"badPasses":[1],"period":[4],"defensiveRebounds":[0],"breaks":[0],"blocks":[0],"badHands":[0],"missedGoalTurnover":[0],"squadId":[8120],"startingPositionCode":["WA"],"goalAttempts":[0],"deflections":[0],"contactPenalties":[0],"quartersPlayed":[1],"minutesPlayed":[15],"turnovers":[1],"pickups":[0],"currentPositionCode":["C"],"intercepts":[0]},{"rebounds":[0],"penalties":[1],"gain":[1],"offensiveRebounds":[0],"possessions":[7],"goalMisses":[0],"blocked":[0],"passes":[7],"goalAssists":[1],"tossUpWin":[0],"disposals":[7],"centrePassReceives":[5],"obstructionPenalties":[1],"feeds":[7],"playerId":[80214],"goals":[0],"offsides":[0],"badPasses":[0],"period":[1],"defensiveRebounds":[0],"breaks":[0],"blocks":[0],"badHands":[0],"missedGoalTurnover":[0],"squadId":[8120],"startingPositionCode":["WA"],"goalAttempts":[0],"deflections":[0],"contactPenalties":[0],"quartersPlayed":[1],"minutesPlayed":[15],"turnovers":[0],"pickups":[1],"currentPositionCode":["WA"],"intercepts":[1]},{"rebounds":[0],"penalties":[2],"gain":[0],"offensiveRebounds":[0],"possessions":[4],"goalMisses":[0],"blocked":[0],"passes":[7],"goalAssists":[5],"tossUpWin":[0],"disposals":[7],"centrePassReceives":[4],"obstructionPenalties":[0],"feeds":[7],"playerId":[80214],"goals":[0],"offsides":[1],"badPasses":[1],"period":[2],"defensiveRebounds":[0],"breaks":[0],"blocks":[0],"badHands":[0],"missedGoalTurnover":[0],"squadId":[8120],"startingPositionCode":["WA"],"goalAttempts":[0],"deflections":[0],"contactPenalties":[2],"quartersPlayed":[1],"minutesPlayed":[15],"turnovers":[2],"pickups":[0],"currentPositionCode":["WA"],"intercepts":[0]},{"rebounds":[0],"penalties":[2],"gain":[0],"offensiveRebounds":[0],"possessions":[2],"goalMisses":[0],"blocked":[0],"passes":[1],"goalAssists":[0],"tossUpWin":[0],"disposals":[1],"centrePassReceives":[2],"obstructionPenalties":[1],"feeds":[1],"playerId":[80214],"goals":[0],"offsides":[0],"badPasses":[0],"period":[3],"defensiveRebounds":[0],"breaks":[0],"blocks":[0],"badHands":[0],"missedGoalTurnover":[0],"squadId":[8120],"startingPositionCode":["WA"],"goalAttempts":[0],"deflections":[0],"contactPenalties":[1],"quartersPlayed":[1],"minutesPlayed":[7],"turnovers":[1],"pickups":[0],"currentPositionCode":["I"],"intercepts":[0]},{"rebounds":[0],"penalties":[0],"gain":[0],"offensiveRebounds":[0],"possessions":[2],"goalMisses":[0],"blocked":[0],"passes":[2],"goalAssists":[0],"tossUpWin":[0],"disposals":[2],"centrePassReceives":[2],"obstructionPenalties":[0],"feeds":[2],"playerId":[80214],"goals":[0],"offsides":[0],"badPasses":[0],"period":[4],"defensiveRebounds":[0],"breaks":[0],"blocks":[0],"badHands":[0],"missedGoalTurnover":[0],"squadId":[8120],"startingPositionCode":["I"],"goalAttempts":[0],"deflections":[0],"contactPenalties":[0],"quartersPlayed":[1],"minutesPlayed":[11],"turnovers":[0],"pickups":[0],"currentPositionCode":["WA"],"intercepts":[0]},{"rebounds":[0],"penalties":[0],"gain":[0],"offensiveRebounds":[0],"possessions":[0],"goalMisses":[0],"blocked":[0],"passes":[0],"goalAssists":[0],"tossUpWin":[0],"disposals":[0],"centrePassReceives":[0],"obstructionPenalties":[0],"feeds":[0],"playerId":[80229],"goals":[0],"offsides":[0],"badPasses":[0],"period":[1],"defensiveRebounds":[0],"breaks":[0],"blocks":[0],"badHands":[0],"missedGoalTurnover":[0],"squadId":[8120],"startingPositionCode":["I"],"goalAttempts":[0],"deflections":[0],"contactPenalties":[0],"quartersPlayed":[0],"minutesPlayed":[0],"turnovers":[0],"pickups":[0],"currentPositionCode":["I"],"intercepts":[0]},{"rebounds":[0],"penalties":[1],"gain":[0],"offensiveRebounds":[0],"possessions":[2],"goalMisses":[1],"blocked":[0],"passes":[0],"goalAssists":[0],"tossUpWin":[0],"disposals":[1],"centrePassReceives":[1],"obstructionPenalties":[0],"feeds":[0],"playerId":[80229],"goals":[0],"offsides":[0],"badPasses":[0],"period":[2],"defensiveRebounds":[0],"breaks":[0],"blocks":[0],"badHands":[0],"missedGoalTurnover":[0],"squadId":[8120],"startingPositionCode":["I"],"goalAttempts":[1],"deflections":[0],"contactPenalties":[1],"quartersPlayed":[1],"minutesPlayed":[5],"turnovers":[2],"pickups":[0],"currentPositionCode":["I"],"intercepts":[0]},{"rebounds":[0],"penalties":[0],"gain":[0],"offensiveRebounds":[0],"possessions":[0],"goalMisses":[0],"blocked":[0],"passes":[0],"goalAssists":[0],"tossUpWin":[0],"disposals":[0],"centrePassReceives":[0],"obstructionPenalties":[0],"feeds":[0],"playerId":[80229],"goals":[0],"offsides":[0],"badPasses":[0],"period":[3],"defensiveRebounds":[0],"breaks":[0],"blocks":[0],"badHands":[0],"missedGoalTurnover":[0],"squadId":[8120],"startingPositionCode":["I"],"goalAttempts":[0],"deflections":[0],"contactPenalties":[0],"quartersPlayed":[0],"minutesPlayed":[0],"turnovers":[0],"pickups":[0],"currentPositionCode":["I"],"intercepts":[0]},{"rebounds":[0],"penalties":[0],"gain":[0],"offensiveRebounds":[0],"possessions":[0],"goalMisses":[0],"blocked":[0],"passes":[0],"goalAssists":[0],"tossUpWin":[0],"disposals":[0],"centrePassReceives":[0],"obstructionPenalties":[0],"feeds":[0],"playerId":[80229],"goals":[0],"offsides":[0],"badPasses":[0],"period":[4],"defensiveRebounds":[0],"breaks":[0],"blocks":[0],"badHands":[0],"missedGoalTurnover":[0],"squadId":[8120],"startingPositionCode":["I"],"goalAttempts":[0],"deflections":[0],"contactPenalties":[0],"quartersPlayed":[0],"minutesPlayed":[0],"turnovers":[0],"pickups":[0],"currentPositionCode":["I"],"intercepts":[0]},{"rebounds":[0],"penalties":[7],"gain":[0],"offensiveRebounds":[0],"possessions":[4],"goalMisses":[0],"blocked":[0],"passes":[0],"goalAssists":[0],"tossUpWin":[0],"disposals":[0],"centrePassReceives":[4],"obstructionPenalties":[4],"feeds":[0],"playerId":[80304],"goals":[0],"offsides":[0],"badPasses":[0],"period":[1],"defensiveRebounds":[0],"breaks":[0],"blocks":[0],"badHands":[0],"missedGoalTurnover":[0],"squadId":[8120],"startingPositionCode":["WD"],"goalAttempts":[0],"deflections":[0],"contactPenalties":[3],"quartersPlayed":[1],"minutesPlayed":[15],"turnovers":[0],"pickups":[0],"currentPositionCode":["WD"],"intercepts":[0]},{"rebounds":[0],"penalties":[4],"gain":[1],"offensiveRebounds":[0],"possessions":[5],"goalMisses":[0],"blocked":[0],"passes":[0],"goalAssists":[0],"tossUpWin":[0],"disposals":[1],"centrePassReceives":[4],"obstructionPenalties":[1],"feeds":[0],"playerId":[80304],"goals":[0],"offsides":[0],"badPasses":[0],"period":[2],"defensiveRebounds":[0],"breaks":[0],"blocks":[0],"badHands":[0],"missedGoalTurnover":[0],"squadId":[8120],"startingPositionCode":["WD"],"goalAttempts":[0],"deflections":[2],"contactPenalties":[3],"quartersPlayed":[1],"minutesPlayed":[15],"turnovers":[0],"pickups":[0],"currentPositionCode":["WD"],"intercepts":[0]},{"rebounds":[0],"penalties":[3],"gain":[1],"offensiveRebounds":[0],"possessions":[3],"goalMisses":[0],"blocked":[0],"passes":[0],"goalAssists":[0],"tossUpWin":[0],"disposals":[0],"centrePassReceives":[2],"obstructionPenalties":[1],"feeds":[0],"playerId":[80304],"goals":[0],"offsides":[0],"badPasses":[1],"period":[3],"defensiveRebounds":[0],"breaks":[0],"blocks":[0],"badHands":[0],"missedGoalTurnover":[0],"squadId":[8120],"startingPositionCode":["WD"],"goalAttempts":[0],"deflections":[0],"contactPenalties":[2],"quartersPlayed":[1],"minutesPlayed":[15],"turnovers":[1],"pickups":[0],"currentPositionCode":["WD"],"intercepts":[1]},{"rebounds":[0],"penalties":[1],"gain":[0],"offensiveRebounds":[0],"possessions":[3],"goalMisses":[0],"blocked":[0],"passes":[0],"goalAssists":[0],"tossUpWin":[0],"disposals":[0],"centrePassReceives":[3],"obstructionPenalties":[0],"feeds":[0],"playerId":[80304],"goals":[0],"offsides":[0],"badPasses":[1],"period":[4],"defensiveRebounds":[0],"breaks":[1],"blocks":[0],"badHands":[0],"missedGoalTurnover":[0],"squadId":[8120],"startingPositionCode":["WD"],"goalAttempts":[0],"deflections":[1],"contactPenalties":[1],"quartersPlayed":[1],"minutesPlayed":[15],"turnovers":[2],"pickups":[0],"currentPositionCode":["WD"],"intercepts":[0]},{"rebounds":[0],"penalties":[5],"gain":[1],"offensiveRebounds":[0],"possessions":[3],"goalMisses":[0],"blocked":[0],"passes":[0],"goalAssists":[0],"tossUpWin":[0],"disposals":[2],"centrePassReceives":[0],"obstructionPenalties":[2],"feeds":[0],"playerId":[80305],"goals":[0],"offsides":[0],"badPasses":[0],"period":[1],"defensiveRebounds":[0],"breaks":[0],"blocks":[0],"badHands":[0],"missedGoalTurnover":[0],"squadId":[8120],"startingPositionCode":["GK"],"goalAttempts":[0],"deflections":[0],"contactPenalties":[3],"quartersPlayed":[1],"minutesPlayed":[15],"turnovers":[0],"pickups":[0],"currentPositionCode":["GK"],"intercepts":[1]},{"rebounds":[1],"penalties":[3],"gain":[1],"offensiveRebounds":[0],"possessions":[4],"goalMisses":[0],"blocked":[0],"passes":[0],"goalAssists":[0],"tossUpWin":[0],"disposals":[3],"centrePassReceives":[0],"obstructionPenalties":[1],"feeds":[0],"playerId":[80305],"goals":[0],"offsides":[0],"badPasses":[0],"period":[2],"defensiveRebounds":[1],"breaks":[0],"blocks":[0],"badHands":[0],"missedGoalTurnover":[0],"squadId":[8120],"startingPositionCode":["GK"],"goalAttempts":[0],"deflections":[2],"contactPenalties":[2],"quartersPlayed":[1],"minutesPlayed":[15],"turnovers":[0],"pickups":[0],"currentPositionCode":["GK"],"intercepts":[0]},{"rebounds":[3],"penalties":[0],"gain":[4],"offensiveRebounds":[0],"possessions":[7],"goalMisses":[0],"blocked":[0],"passes":[0],"goalAssists":[0],"tossUpWin":[0],"disposals":[1],"centrePassReceives":[0],"obstructionPenalties":[0],"feeds":[0],"playerId":[80305],"goals":[0],"offsides":[0],"badPasses":[0],"period":[3],"defensiveRebounds":[3],"breaks":[0],"blocks":[0],"badHands":[0],"missedGoalTurnover":[0],"squadId":[8120],"startingPositionCode":["GK"],"goalAttempts":[0],"deflections":[0],"contactPenalties":[0],"quartersPlayed":[1],"minutesPlayed":[15],"turnovers":[0],"pickups":[1],"currentPositionCode":["GK"],"intercepts":[1]},{"rebounds":[2],"penalties":[1],"gain":[2],"offensiveRebounds":[0],"possessions":[2],"goalMisses":[0],"blocked":[0],"passes":[0],"goalAssists":[0],"tossUpWin":[0],"disposals":[0],"centrePassReceives":[0],"obstructionPenalties":[0],"feeds":[0],"playerId":[80305],"goals":[0],"offsides":[0],"badPasses":[0],"period":[4],"defensiveRebounds":[2],"breaks":[0],"blocks":[0],"badHands":[0],"missedGoalTurnover":[0],"squadId":[8120],"startingPositionCode":["GK"],"goalAttempts":[0],"deflections":[0],"contactPenalties":[1],"quartersPlayed":[1],"minutesPlayed":[15],"turnovers":[0],"pickups":[0],"currentPositionCode":["GK"],"intercepts":[0]},{"rebounds":[1],"penalties":[0],"gain":[0],"offensiveRebounds":[1],"possessions":[6],"goalMisses":[1],"blocked":[0],"passes":[1],"goalAssists":[1],"tossUpWin":[0],"disposals":[6],"centrePassReceives":[0],"obstructionPenalties":[0],"feeds":[1],"playerId":[80710],"goals":[4],"offsides":[0],"badPasses":[0],"period":[1],"defensiveRebounds":[0],"breaks":[0],"blocks":[0],"badHands":[0],"missedGoalTurnover":[0],"squadId":[8120],"startingPositionCode":["GS"],"goalAttempts":[5],"deflections":[0],"contactPenalties":[0],"quartersPlayed":[1],"minutesPlayed":[15],"turnovers":[2],"pickups":[0],"currentPositionCode":["GS"],"intercepts":[0]},{"rebounds":[0],"penalties":[0],"gain":[0],"offensiveRebounds":[0],"possessions":[8],"goalMisses":[1],"blocked":[0],"passes":[2],"goalAssists":[1],"tossUpWin":[0],"disposals":[10],"centrePassReceives":[0],"obstructionPenalties":[0],"feeds":[2],"playerId":[80710],"goals":[7],"offsides":[0],"badPasses":[0],"period":[2],"defensiveRebounds":[0],"breaks":[0],"blocks":[0],"badHands":[0],"missedGoalTurnover":[0],"squadId":[8120],"startingPositionCode":["GS"],"goalAttempts":[8],"deflections":[0],"contactPenalties":[0],"quartersPlayed":[1],"minutesPlayed":[15],"turnovers":[1],"pickups":[0],"currentPositionCode":["GS"],"intercepts":[0]},{"rebounds":[0],"penalties":[0],"gain":[0],"offensiveRebounds":[0],"possessions":[12],"goalMisses":[1],"blocked":[0],"passes":[0],"goalAssists":[0],"tossUpWin":[0],"disposals":[12],"centrePassReceives":[0],"obstructionPenalties":[0],"feeds":[0],"playerId":[80710],"goals":[11],"offsides":[0],"badPasses":[0],"period":[3],"defensiveRebounds":[0],"breaks":[0],"blocks":[0],"badHands":[0],"missedGoalTurnover":[0],"squadId":[8120],"startingPositionCode":["GS"],"goalAttempts":[12],"deflections":[0],"contactPenalties":[0],"quartersPlayed":[1],"minutesPlayed":[15],"turnovers":[0],"pickups":[0],"currentPositionCode":["GS"],"intercepts":[0]},{"rebounds":[2],"penalties":[1],"gain":[0],"offensiveRebounds":[2],"possessions":[14],"goalMisses":[2],"blocked":[0],"passes":[2],"goalAssists":[1],"tossUpWin":[0],"disposals":[14],"centrePassReceives":[0],"obstructionPenalties":[1],"feeds":[2],"playerId":[80710],"goals":[10],"offsides":[0],"badPasses":[0],"period":[4],"defensiveRebounds":[0],"breaks":[0],"blocks":[0],"badHands":[1],"missedGoalTurnover":[0],"squadId":[8120],"startingPositionCode":["GS"],"goalAttempts":[12],"deflections":[0],"contactPenalties":[0],"quartersPlayed":[1],"minutesPlayed":[15],"turnovers":[2],"pickups":[0],"currentPositionCode":["GS"],"intercepts":[0]},{"rebounds":[0],"penalties":[0],"gain":[0],"offensiveRebounds":[0],"possessions":[0],"goalMisses":[0],"blocked":[0],"passes":[0],"goalAssists":[0],"tossUpWin":[0],"disposals":[0],"centrePassReceives":[0],"obstructionPenalties":[0],"feeds":[0],"playerId":[80808],"goals":[0],"offsides":[0],"badPasses":[0],"period":[1],"defensiveRebounds":[0],"breaks":[0],"blocks":[0],"badHands":[0],"missedGoalTurnover":[0],"squadId":[8120],"startingPositionCode":["I"],"goalAttempts":[0],"deflections":[0],"contactPenalties":[0],"quartersPlayed":[0],"minutesPlayed":[0],"turnovers":[0],"pickups":[0],"currentPositionCode":["I"],"intercepts":[0]},{"rebounds":[0],"penalties":[0],"gain":[0],"offensiveRebounds":[0],"possessions":[0],"goalMisses":[0],"blocked":[0],"passes":[0],"goalAssists":[0],"tossUpWin":[0],"disposals":[0],"centrePassReceives":[0],"obstructionPenalties":[0],"feeds":[0],"playerId":[80808],"goals":[0],"offsides":[0],"badPasses":[0],"period":[2],"defensiveRebounds":[0],"breaks":[0],"blocks":[0],"badHands":[0],"missedGoalTurnover":[0],"squadId":[8120],"startingPositionCode":["I"],"goalAttempts":[0],"deflections":[0],"contactPenalties":[0],"quartersPlayed":[0],"minutesPlayed":[0],"turnovers":[0],"pickups":[0],"currentPositionCode":["I"],"intercepts":[0]},{"rebounds":[0],"penalties":[0],"gain":[0],"offensiveRebounds":[0],"possessions":[0],"goalMisses":[0],"blocked":[0],"passes":[0],"goalAssists":[0],"tossUpWin":[0],"disposals":[0],"centrePassReceives":[0],"obstructionPenalties":[0],"feeds":[0],"playerId":[80808],"goals":[0],"offsides":[0],"badPasses":[0],"period":[3],"defensiveRebounds":[0],"breaks":[0],"blocks":[0],"badHands":[0],"missedGoalTurnover":[0],"squadId":[8120],"startingPositionCode":["I"],"goalAttempts":[0],"deflections":[0],"contactPenalties":[0],"quartersPlayed":[0],"minutesPlayed":[0],"turnovers":[0],"pickups":[0],"currentPositionCode":["I"],"intercepts":[0]},{"rebounds":[0],"penalties":[0],"gain":[0],"offensiveRebounds":[0],"possessions":[0],"goalMisses":[0],"blocked":[0],"passes":[0],"goalAssists":[0],"tossUpWin":[0],"disposals":[0],"centrePassReceives":[0],"obstructionPenalties":[0],"feeds":[0],"playerId":[80808],"goals":[0],"offsides":[0],"badPasses":[0],"period":[4],"defensiveRebounds":[0],"breaks":[0],"blocks":[0],"badHands":[0],"missedGoalTurnover":[0],"squadId":[8120],"startingPositionCode":["I"],"goalAttempts":[0],"deflections":[0],"contactPenalties":[0],"quartersPlayed":[0],"minutesPlayed":[0],"turnovers":[0],"pickups":[0],"currentPositionCode":["I"],"intercepts":[0]},{"rebounds":[0],"penalties":[0],"gain":[0],"offensiveRebounds":[0],"possessions":[13],"goalMisses":[4],"blocked":[0],"passes":[1],"goalAssists":[1],"tossUpWin":[0],"disposals":[14],"centrePassReceives":[0],"obstructionPenalties":[0],"feeds":[1],"playerId":[991906],"goals":[7],"offsides":[0],"badPasses":[0],"period":[1],"defensiveRebounds":[0],"breaks":[0],"blocks":[0],"badHands":[0],"missedGoalTurnover":[0],"squadId":[8120],"startingPositionCode":["GA"],"goalAttempts":[11],"deflections":[0],"contactPenalties":[0],"quartersPlayed":[1],"minutesPlayed":[15],"turnovers":[2],"pickups":[0],"currentPositionCode":["GA"],"intercepts":[0]},{"rebounds":[0],"penalties":[1],"gain":[0],"offensiveRebounds":[0],"possessions":[8],"goalMisses":[0],"blocked":[0],"passes":[4],"goalAssists":[3],"tossUpWin":[0],"disposals":[9],"centrePassReceives":[3],"obstructionPenalties":[1],"feeds":[4],"playerId":[991906],"goals":[4],"offsides":[0],"badPasses":[1],"period":[2],"defensiveRebounds":[0],"breaks":[0],"blocks":[0],"badHands":[0],"missedGoalTurnover":[0],"squadId":[8120],"startingPositionCode":["GA"],"goalAttempts":[4],"deflections":[0],"contactPenalties":[0],"quartersPlayed":[1],"minutesPlayed":[11],"turnovers":[1],"pickups":[0],"currentPositionCode":["GA"],"intercepts":[0]},{"rebounds":[0],"penalties":[3],"gain":[0],"offensiveRebounds":[0],"possessions":[7],"goalMisses":[0],"blocked":[0],"passes":[4],"goalAssists":[3],"tossUpWin":[0],"disposals":[7],"centrePassReceives":[4],"obstructionPenalties":[2],"feeds":[4],"playerId":[991906],"goals":[3],"offsides":[0],"badPasses":[0],"period":[3],"defensiveRebounds":[0],"breaks":[0],"blocks":[0],"badHands":[0],"missedGoalTurnover":[0],"squadId":[8120],"startingPositionCode":["GA"],"goalAttempts":[3],"deflections":[1],"contactPenalties":[1],"quartersPlayed":[1],"minutesPlayed":[15],"turnovers":[1],"pickups":[0],"currentPositionCode":["GA"],"intercepts":[0]},{"rebounds":[0],"penalties":[1],"gain":[0],"offensiveRebounds":[0],"possessions":[10],"goalMisses":[2],"blocked":[0],"passes":[5],"goalAssists":[3],"tossUpWin":[0],"disposals":[12],"centrePassReceives":[2],"obstructionPenalties":[0],"feeds":[5],"playerId":[991906],"goals":[3],"offsides":[0],"badPasses":[0],"period":[4],"defensiveRebounds":[0],"breaks":[0],"blocks":[0],"badHands":[0],"missedGoalTurnover":[0],"squadId":[8120],"startingPositionCode":["GA"],"goalAttempts":[5],"deflections":[0],"contactPenalties":[1],"quartersPlayed":[1],"minutesPlayed":[15],"turnovers":[1],"pickups":[1],"currentPositionCode":["GA"],"intercepts":[0]},{"rebounds":[0],"penalties":[0],"gain":[0],"offensiveRebounds":[0],"possessions":[0],"goalMisses":[0],"blocked":[0],"passes":[0],"goalAssists":[0],"tossUpWin":[0],"disposals":[0],"centrePassReceives":[0],"obstructionPenalties":[0],"feeds":[0],"playerId":[998998],"goals":[0],"offsides":[0],"badPasses":[0],"period":[1],"defensiveRebounds":[0],"breaks":[0],"blocks":[0],"badHands":[0],"missedGoalTurnover":[0],"squadId":[8120],"startingPositionCode":["I"],"goalAttempts":[0],"deflections":[0],"contactPenalties":[0],"quartersPlayed":[0],"minutesPlayed":[0],"turnovers":[0],"pickups":[0],"currentPositionCode":["I"],"intercepts":[0]},{"rebounds":[0],"penalties":[0],"gain":[0],"offensiveRebounds":[0],"possessions":[0],"goalMisses":[0],"blocked":[0],"passes":[0],"goalAssists":[0],"tossUpWin":[0],"disposals":[0],"centrePassReceives":[0],"obstructionPenalties":[0],"feeds":[0],"playerId":[998998],"goals":[0],"offsides":[0],"badPasses":[0],"period":[2],"defensiveRebounds":[0],"breaks":[0],"blocks":[0],"badHands":[0],"missedGoalTurnover":[0],"squadId":[8120],"startingPositionCode":["I"],"goalAttempts":[0],"deflections":[0],"contactPenalties":[0],"quartersPlayed":[0],"minutesPlayed":[0],"turnovers":[0],"pickups":[0],"currentPositionCode":["I"],"intercepts":[0]},{"rebounds":[0],"penalties":[3],"gain":[0],"offensiveRebounds":[0],"possessions":[0],"goalMisses":[0],"blocked":[0],"passes":[7],"goalAssists":[2],"tossUpWin":[0],"disposals":[7],"centrePassReceives":[0],"obstructionPenalties":[0],"feeds":[7],"playerId":[998998],"goals":[0],"offsides":[0],"badPasses":[0],"period":[3],"defensiveRebounds":[0],"breaks":[0],"blocks":[0],"badHands":[0],"missedGoalTurnover":[0],"squadId":[8120],"startingPositionCode":["I"],"goalAttempts":[0],"deflections":[1],"contactPenalties":[3],"quartersPlayed":[1],"minutesPlayed":[9],"turnovers":[1],"pickups":[0],"currentPositionCode":["C"],"intercepts":[0]},{"rebounds":[0],"penalties":[0],"gain":[0],"offensiveRebounds":[0],"possessions":[0],"goalMisses":[0],"blocked":[0],"passes":[2],"goalAssists":[2],"tossUpWin":[0],"disposals":[2],"centrePassReceives":[0],"obstructionPenalties":[0],"feeds":[2],"playerId":[998998],"goals":[0],"offsides":[0],"badPasses":[1],"period":[4],"defensiveRebounds":[0],"breaks":[0],"blocks":[0],"badHands":[0],"missedGoalTurnover":[0],"squadId":[8120],"startingPositionCode":["C"],"goalAttempts":[0],"deflections":[0],"contactPenalties":[0],"quartersPlayed":[1],"minutesPlayed":[5],"turnovers":[1],"pickups":[0],"currentPositionCode":["I"],"intercepts":[0]}]},"periodInfo":{"qtr":[{"period":[1],"periodSeconds":[911]},{"period":[2],"periodSeconds":[912]},{"period":[3],"periodSeconds":[920]},{"period":[4],"periodSeconds":[906]}]},"teamInfo":{"team":[{"squadName":["Silvermoon Tactix"],"squadNickname":["Tactix"],"squadCode":["TAC"],"squadId":[802]},{"squadName":["Northern Stars"],"squadNickname":["Stars"],"squadCode":["NS"],"squadId":[8120]}]},"teamPeriodStats":{"team":[{"rebounds":[5],"goalsFromCentrePass":[7],"goalsFromTurnovers":[0],"penalties":[23],"timeInPossession":[49],"gain":[5],"offensiveRebounds":[2],"possessions":[36],"goalMisses":[4],"blocked":[0],"passes":[21],"goalAssists":[6],"tossUpWin":[0],"disposals":[37],"centrePassReceives":[11],"obstructionPenalties":[9],"feeds":[21],"goals":[10],"offsides":[1],"badPasses":[1],"period":[1],"defensiveRebounds":[3],"breaks":[0],"blocks":[0],"badHands":[0],"goalsFromGain":[3],"squadId":[802],"goalAttempts":[14],"deflections":[5],"contactPenalties":[14],"turnovers":[7],"pickups":[2],"intercepts":[1]},{"rebounds":[3],"goalsFromCentrePass":[5],"goalsFromTurnovers":[5],"penalties":[5],"timeInPossession":[50],"gain":[7],"offensiveRebounds":[1],"possessions":[41],"goalMisses":[2],"blocked":[0],"passes":[23],"goalAssists":[9],"tossUpWin":[0],"disposals":[43],"centrePassReceives":[12],"obstructionPenalties":[0],"feeds":[23],"goals":[12],"offsides":[0],"badPasses":[4],"period":[2],"defensiveRebounds":[2],"breaks":[0],"blocks":[0],"badHands":[4],"goalsFromGain":[2],"squadId":[802],"goalAttempts":[14],"deflections":[2],"contactPenalties":[5],"turnovers":[12],"pickups":[1],"intercepts":[4]},{"rebounds":[0],"goalsFromCentrePass":[4],"goalsFromTurnovers":[3],"penalties":[13],"timeInPossession":[45],"gain":[6],"offensiveRebounds":[0],"possessions":[33],"goalMisses":[4],"blocked":[0],"passes":[27],"goalAssists":[9],"tossUpWin":[0],"disposals":[43],"centrePassReceives":[10],"obstructionPenalties":[2],"feeds":[27],"goals":[9],"offsides":[0],"badPasses":[1],"period":[3],"defensiveRebounds":[0],"breaks":[0],"blocks":[0],"badHands":[1],"goalsFromGain":[2],"squadId":[802],"goalAttempts":[13],"deflections":[2],"contactPenalties":[11],"turnovers":[11],"pickups":[2],"intercepts":[4]},{"rebounds":[1],"goalsFromCentrePass":[9],"goalsFromTurnovers":[4],"penalties":[20],"timeInPossession":[47],"gain":[1],"offensiveRebounds":[0],"possessions":[34],"goalMisses":[4],"blocked":[0],"passes":[26],"goalAssists":[10],"tossUpWin":[0],"disposals":[47],"centrePassReceives":[11],"obstructionPenalties":[3],"feeds":[26],"goals":[13],"offsides":[1],"badPasses":[1],"period":[4],"defensiveRebounds":[1],"breaks":[1],"blocks":[0],"badHands":[0],"goalsFromGain":[0],"squadId":[802],"goalAttempts":[17],"deflections":[3],"contactPenalties":[17],"turnovers":[6],"pickups":[1],"intercepts":[0]},{"rebounds":[0],"goalsFromCentrePass":[0],"goalsFromTurnovers":[0],"penalties":[0],"timeInPossession":[0],"gain":[0],"offensiveRebounds":[0],"possessions":[0],"goalMisses":[0],"blocked":[0],"passes":[0],"goalAssists":[0],"tossUpWin":[0],"disposals":[0],"centrePassReceives":[0],"obstructionPenalties":[0],"feeds":[0],"goals":[0],"offsides":[0],"badPasses":[0],"period":[5],"defensiveRebounds":[0],"breaks":[0],"blocks":[0],"badHands":[0],"goalsFromGain":[0],"squadId":[802],"goalAttempts":[0],"deflections":[0],"contactPenalties":[0],"turnovers":[0],"pickups":[0],"intercepts":[0]},{"rebounds":[0],"goalsFromCentrePass":[0],"goalsFromTurnovers":[0],"penalties":[0],"timeInPossession":[0],"gain":[0],"offensiveRebounds":[0],"possessions":[0],"goalMisses":[0],"blocked":[0],"passes":[0],"goalAssists":[0],"tossUpWin":[0],"disposals":[0],"centrePassReceives":[0],"obstructionPenalties":[0],"feeds":[0],"goals":[0],"offsides":[0],"badPasses":[0],"period":[6],"defensiveRebounds":[0],"breaks":[0],"blocks":[0],"badHands":[0],"goalsFromGain":[0],"squadId":[802],"goalAttempts":[0],"deflections":[0],"contactPenalties":[0],"turnovers":[0],"pickups":[0],"intercepts":[0]},{"rebounds":[1],"goalsFromCentrePass":[6],"goalsFromTurnovers":[4],"penalties":[16],"timeInPossession":[51],"gain":[2],"offensiveRebounds":[1],"possessions":[34],"goalMisses":[5],"blocked":[0],"passes":[15],"goalAssists":[5],"tossUpWin":[0],"disposals":[35],"centrePassReceives":[9],"obstructionPenalties":[7],"feeds":[15],"goals":[11],"offsides":[0],"badPasses":[0],"period":[1],"defensiveRebounds":[0],"breaks":[0],"blocks":[0],"badHands":[0],"goalsFromGain":[1],"squadId":[8120],"goalAttempts":[16],"deflections":[3],"contactPenalties":[9],"turnovers":[6],"pickups":[2],"intercepts":[2]},{"rebounds":[1],"goalsFromCentrePass":[2],"goalsFromTurnovers":[7],"penalties":[16],"timeInPossession":[50],"gain":[4],"offensiveRebounds":[0],"possessions":[39],"goalMisses":[2],"blocked":[0],"passes":[18],"goalAssists":[11],"tossUpWin":[0],"disposals":[37],"centrePassReceives":[12],"obstructionPenalties":[4],"feeds":[18],"goals":[11],"offsides":[1],"badPasses":[2],"period":[2],"defensiveRebounds":[1],"breaks":[0],"blocks":[0],"badHands":[1],"goalsFromGain":[2],"squadId":[8120],"goalAttempts":[13],"deflections":[4],"contactPenalties":[12],"turnovers":[12],"pickups":[3],"intercepts":[2]},{"rebounds":[4],"goalsFromCentrePass":[8],"goalsFromTurnovers":[1],"penalties":[12],"timeInPossession":[55],"gain":[8],"offensiveRebounds":[0],"possessions":[40],"goalMisses":[1],"blocked":[0],"passes":[22],"goalAssists":[8],"tossUpWin":[0],"disposals":[39],"centrePassReceives":[12],"obstructionPenalties":[4],"feeds":[22],"goals":[14],"offsides":[0],"badPasses":[1],"period":[3],"defensiveRebounds":[4],"breaks":[0],"blocks":[0],"badHands":[0],"goalsFromGain":[5],"squadId":[8120],"goalAttempts":[15],"deflections":[4],"contactPenalties":[8],"turnovers":[9],"pickups":[2],"intercepts":[3]},{"rebounds":[6],"goalsFromCentrePass":[9],"goalsFromTurnovers":[1],"penalties":[6],"timeInPossession":[53],"gain":[4],"offensiveRebounds":[2],"possessions":[39],"goalMisses":[4],"blocked":[0],"passes":[17],"goalAssists":[10],"tossUpWin":[0],"disposals":[37],"centrePassReceives":[12],"obstructionPenalties":[1],"feeds":[17],"goals":[13],"offsides":[0],"badPasses":[3],"period":[4],"defensiveRebounds":[4],"breaks":[1],"blocks":[0],"badHands":[1],"goalsFromGain":[3],"squadId":[8120],"goalAttempts":[17],"deflections":[1],"contactPenalties":[5],"turnovers":[7],"pickups":[1],"intercepts":[0]},{"rebounds":[0],"goalsFromCentrePass":[0],"goalsFromTurnovers":[0],"penalties":[0],"timeInPossession":[0],"gain":[0],"offensiveRebounds":[0],"possessions":[0],"goalMisses":[0],"blocked":[0],"passes":[0],"goalAssists":[0],"tossUpWin":[0],"disposals":[0],"centrePassReceives":[0],"obstructionPenalties":[0],"feeds":[0],"goals":[0],"offsides":[0],"badPasses":[0],"period":[5],"defensiveRebounds":[0],"breaks":[0],"blocks":[0],"badHands":[0],"goalsFromGain":[0],"squadId":[8120],"goalAttempts":[0],"deflections":[0],"contactPenalties":[0],"turnovers":[0],"pickups":[0],"intercepts":[0]},{"rebounds":[0],"goalsFromCentrePass":[0],"goalsFromTurnovers":[0],"penalties":[0],"timeInPossession":[0],"gain":[0],"offensiveRebounds":[0],"possessions":[0],"goalMisses":[0],"blocked":[0],"passes":[0],"goalAssists":[0],"tossUpWin":[0],"disposals":[0],"centrePassReceives":[0],"obstructionPenalties":[0],"feeds":[0],"goals":[0],"offsides":[0],"badPasses":[0],"period":[6],"defensiveRebounds":[0],"breaks":[0],"blocks":[0],"badHands":[0],"goalsFromGain":[0],"squadId":[8120],"goalAttempts":[0],"deflections":[0],"contactPenalties":[0],"turnovers":[0],"pickups":[0],"intercepts":[0]}]},"teamStats":{"team":[{"rebounds":[9],"goalsFromCentrePass":[25],"goalsFromTurnovers":[12],"penalties":[61],"timeInPossession":[48],"gain":[19],"possessions":[144],"offensiveRebounds":[3],"goalMisses":[14],"blocked":[0],"passes":[97],"goalAssists":[34],"disposals":[170],"tossUpWin":[0],"centrePassReceives":[44],"obstructionPenalties":[14],"feeds":[97],"goals":[44],"offsides":[2],"badPasses":[7],"defensiveRebounds":[6],"breaks":[1],"blocks":[0],"badHands":[5],"missedGoalTurnover":[0],"goalsFromGain":[7],"squadId":[802],"goalAttempts":[58],"deflections":[12],"contactPenalties":[47],"turnovers":[36],"pickups":[6],"intercepts":[9]},{"rebounds":[12],"goalsFromCentrePass":[25],"goalsFromTurnovers":[13],"penalties":[50],"timeInPossession":[52],"gain":[18],"possessions":[152],"offensiveRebounds":[3],"goalMisses":[12],"blocked":[0],"passes":[72],"goalAssists":[34],"disposals":[148],"tossUpWin":[0],"centrePassReceives":[45],"obstructionPenalties":[16],"feeds":[72],"goals":[49],"offsides":[1],"badPasses":[6],"defensiveRebounds":[9],"breaks":[1],"blocks":[0],"badHands":[2],"missedGoalTurnover":[0],"goalsFromGain":[11],"squadId":[8120],"goalAttempts":[61],"deflections":[12],"contactPenalties":[34],"turnovers":[34],"pickups":[8],"intercepts":[7]}]},"playerSubs":{"player":[{"period":[1],"periodSeconds":[719],"fromPos":["GA"],"squadId":[802],"playerId":[80028],"toPos":["S"]},{"period":[1],"periodSeconds":[719],"fromPos":["S"],"squadId":[802],"playerId":[80532],"toPos":["GA"]},{"period":[2],"periodSeconds":[640],"fromPos":["GS"],"squadId":[802],"playerId":[80469],"toPos":["S"]},{"period":[2],"periodSeconds":[640],"fromPos":["S"],"squadId":[8120],"playerId":[80229],"toPos":["GA"]},{"period":[2],"periodSeconds":[640],"fromPos":["S"],"squadId":[802],"playerId":[80028],"toPos":["GA"]},{"period":[2],"periodSeconds":[640],"fromPos":["GA"],"squadId":[8120],"playerId":[991906],"toPos":["S"]},{"period":[2],"periodSeconds":[640],"fromPos":["GA"],"squadId":[802],"playerId":[80532],"toPos":["GS"]},{"period":[3],"periodSeconds":[0],"fromPos":["S"],"squadId":[8120],"playerId":[991906],"toPos":["GA"]},{"period":[3],"periodSeconds":[0],"fromPos":["GA"],"squadId":[8120],"playerId":[80229],"toPos":["S"]},{"period":[3],"periodSeconds":[382],"fromPos":["S"],"squadId":[8120],"playerId":[998998],"toPos":["C"]},{"period":[3],"periodSeconds":[382],"fromPos":["C"],"squadId":[8120],"playerId":[80182],"toPos":["WA"]},{"period":[3],"periodSeconds":[382],"fromPos":["WA"],"squadId":[8120],"playerId":[80214],"toPos":["S"]},{"period":[4],"periodSeconds":[274],"fromPos":["C"],"squadId":[8120],"playerId":[998998],"toPos":["S"]},{"period":[4],"periodSeconds":[274],"fromPos":["S"],"squadId":[8120],"playerId":[80214],"toPos":["WA"]},{"period":[4],"periodSeconds":[274],"fromPos":["WA"],"squadId":[8120],"playerId":[80182],"toPos":["C"]},{"period":[4],"periodSeconds":[688],"fromPos":["C"],"squadId":[802],"playerId":[80526],"toPos":["S"]},{"period":[4],"periodSeconds":[688],"fromPos":["S"],"squadId":[802],"playerId":[997432],"toPos":["C"]}]},"scoreFlow":{"score":[{"period":[1],"distanceCode":[0],"scorepoints":[1],"periodSeconds":[29],"positionCode":[2],"squadId":[802],"playerId":[80469],"scoreName":["goal"]},{"period":[1],"distanceCode":[0],"scorepoints":[0],"periodSeconds":[134],"positionCode":[1],"squadId":[802],"playerId":[80469],"scoreName":["miss"]},{"period":[1],"distanceCode":[0],"scorepoints":[0],"periodSeconds":[144],"positionCode":[1],"squadId":[802],"playerId":[80469],"scoreName":["miss"]},{"period":[1],"distanceCode":[0],"scorepoints":[1],"periodSeconds":[246],"positionCode":[2],"squadId":[8120],"playerId":[991906],"scoreName":["goal"]},{"period":[1],"distanceCode":[0],"scorepoints":[1],"periodSeconds":[278],"positionCode":[2],"squadId":[8120],"playerId":[991906],"scoreName":["goal"]},{"period":[1],"distanceCode":[0],"scorepoints":[1],"periodSeconds":[312],"positionCode":[1],"squadId":[8120],"playerId":[991906],"scoreName":["goal"]},{"period":[1],"distanceCode":[0],"scorepoints":[0],"periodSeconds":[326],"positionCode":[0],"squadId":[8120],"playerId":[991906],"scoreName":["miss"]},{"period":[1],"distanceCode":[0],"scorepoints":[1],"periodSeconds":[345],"positionCode":[2],"squadId":[8120],"playerId":[80710],"scoreName":["goal"]},{"period":[1],"distanceCode":[0],"scorepoints":[1],"periodSeconds":[377],"positionCode":[2],"squadId":[8120],"playerId":[80710],"scoreName":["goal"]},{"period":[1],"distanceCode":[0],"scorepoints":[0],"periodSeconds":[437],"positionCode":[0],"squadId":[8120],"playerId":[80710],"scoreName":["miss"]},{"period":[1],"distanceCode":[0],"scorepoints":[1],"periodSeconds":[493],"positionCode":[2],"squadId":[802],"playerId":[80028],"scoreName":["goal"]},{"period":[1],"distanceCode":[0],"scorepoints":[0],"periodSeconds":[509],"positionCode":[2],"squadId":[8120],"playerId":[991906],"scoreName":["miss"]},{"period":[1],"distanceCode":[0],"scorepoints":[1],"periodSeconds":[543],"positionCode":[1],"squadId":[802],"playerId":[80028],"scoreName":["goal"]},{"period":[1],"distanceCode":[0],"scorepoints":[1],"periodSeconds":[564],"positionCode":[2],"squadId":[802],"playerId":[80469],"scoreName":["goal"]},{"period":[1],"distanceCode":[0],"scorepoints":[0],"periodSeconds":[587],"positionCode":[0],"squadId":[8120],"playerId":[991906],"scoreName":["miss"]},{"period":[1],"distanceCode":[0],"scorepoints":[1],"periodSeconds":[594],"positionCode":[0],"squadId":[8120],"playerId":[991906],"scoreName":["goal"]},{"period":[1],"distanceCode":[0],"scorepoints":[1],"periodSeconds":[623],"positionCode":[1],"squadId":[802],"playerId":[80469],"scoreName":["goal"]},{"period":[1],"distanceCode":[0],"scorepoints":[1],"periodSeconds":[649],"positionCode":[0],"squadId":[8120],"playerId":[80710],"scoreName":["goal"]},{"period":[1],"distanceCode":[0],"scorepoints":[1],"periodSeconds":[688],"positionCode":[1],"squadId":[8120],"playerId":[991906],"scoreName":["goal"]},{"period":[1],"distanceCode":[0],"scorepoints":[1],"periodSeconds":[714],"positionCode":[0],"squadId":[8120],"playerId":[991906],"scoreName":["goal"]},{"period":[1],"distanceCode":[0],"scorepoints":[1],"periodSeconds":[736],"positionCode":[1],"squadId":[802],"playerId":[80469],"scoreName":["goal"]},{"period":[1],"distanceCode":[0],"scorepoints":[1],"periodSeconds":[757],"positionCode":[2],"squadId":[8120],"playerId":[80710],"scoreName":["goal"]},{"period":[1],"distanceCode":[0],"scorepoints":[0],"periodSeconds":[776],"positionCode":[1],"squadId":[802],"playerId":[80469],"scoreName":["miss"]},{"period":[1],"distanceCode":[0],"scorepoints":[1],"periodSeconds":[784],"positionCode":[1],"squadId":[802],"playerId":[80532],"scoreName":["goal"]},{"period":[1],"distanceCode":[0],"scorepoints":[1],"periodSeconds":[803],"positionCode":[1],"squadId":[8120],"playerId":[991906],"scoreName":["goal"]},{"period":[1],"distanceCode":[0],"scorepoints":[0],"periodSeconds":[843],"positionCode":[2],"squadId":[802],"playerId":[80532],"scoreName":["miss"]},{"period":[1],"distanceCode":[0],"scorepoints":[1],"periodSeconds":[849],"positionCode":[2],"squadId":[802],"playerId":[80532],"scoreName":["goal"]},{"period":[1],"distanceCode":[0],"scorepoints":[0],"periodSeconds":[860],"positionCode":[2],"squadId":[8120],"playerId":[991906],"scoreName":["miss"]},{"period":[1],"distanceCode":[0],"scorepoints":[1],"periodSeconds":[878],"positionCode":[1],"squadId":[802],"playerId":[80469],"scoreName":["goal"]},{"period":[1],"distanceCode":[0],"scorepoints":[1],"periodSeconds":[898],"positionCode":[0],"squadId":[802],"playerId":[80469],"scoreName":["goal"]},{"period":[2],"distanceCode":[0],"scorepoints":[0],"periodSeconds":[39],"positionCode":[0],"squadId":[802],"playerId":[80532],"scoreName":["miss"]},{"period":[2],"distanceCode":[0],"scorepoints":[1],"periodSeconds":[48],"positionCode":[2],"squadId":[802],"playerId":[80469],"scoreName":["goal"]},{"period":[2],"distanceCode":[0],"scorepoints":[1],"periodSeconds":[111],"positionCode":[2],"squadId":[802],"playerId":[80469],"scoreName":["goal"]},{"period":[2],"distanceCode":[0],"scorepoints":[1],"periodSeconds":[179],"positionCode":[2],"squadId":[8120],"playerId":[80710],"scoreName":["goal"]},{"period":[2],"distanceCode":[0],"scorepoints":[1],"periodSeconds":[230],"positionCode":[2],"squadId":[8120],"playerId":[991906],"scoreName":["goal"]},{"period":[2],"distanceCode":[0],"scorepoints":[1],"periodSeconds":[272],"positionCode":[2],"squadId":[8120],"playerId":[991906],"scoreName":["goal"]},{"period":[2],"distanceCode":[0],"scorepoints":[1],"periodSeconds":[307],"positionCode":[1],"squadId":[8120],"playerId":[80710],"scoreName":["goal"]},{"period":[2],"distanceCode":[0],"scorepoints":[1],"periodSeconds":[340],"positionCode":[0],"squadId":[8120],"playerId":[80710],"scoreName":["goal"]},{"period":[2],"distanceCode":[1],"scorepoints":[1],"periodSeconds":[359],"positionCode":[0],"squadId":[802],"playerId":[80532],"scoreName":["goal"]},{"period":[2],"distanceCode":[0],"scorepoints":[0],"periodSeconds":[380],"positionCode":[1],"squadId":[8120],"playerId":[80710],"scoreName":["miss"]},{"period":[2],"distanceCode":[0],"scorepoints":[1],"periodSeconds":[428],"positionCode":[2],"squadId":[8120],"playerId":[80710],"scoreName":["goal"]},{"period":[2],"distanceCode":[0],"scorepoints":[1],"periodSeconds":[443],"positionCode":[0],"squadId":[802],"playerId":[80532],"scoreName":["goal"]},{"period":[2],"distanceCode":[0],"scorepoints":[1],"periodSeconds":[458],"positionCode":[0],"squadId":[8120],"playerId":[991906],"scoreName":["goal"]},{"period":[2],"distanceCode":[0],"scorepoints":[1],"periodSeconds":[493],"positionCode":[2],"squadId":[8120],"playerId":[80710],"scoreName":["goal"]},{"period":[2],"distanceCode":[0],"scorepoints":[1],"periodSeconds":[530],"positionCode":[2],"squadId":[802],"playerId":[80532],"scoreName":["goal"]},{"period":[2],"distanceCode":[0],"scorepoints":[0],"periodSeconds":[562],"positionCode":[2],"squadId":[802],"playerId":[80532],"scoreName":["miss"]},{"period":[2],"distanceCode":[0],"scorepoints":[1],"periodSeconds":[591],"positionCode":[2],"squadId":[8120],"playerId":[991906],"scoreName":["goal"]},{"period":[2],"distanceCode":[0],"scorepoints":[1],"periodSeconds":[637],"positionCode":[0],"squadId":[8120],"playerId":[80710],"scoreName":["goal"]},{"period":[2],"distanceCode":[0],"scorepoints":[1],"periodSeconds":[659],"positionCode":[0],"squadId":[802],"playerId":[80532],"scoreName":["goal"]},{"period":[2],"distanceCode":[0],"scorepoints":[1],"periodSeconds":[686],"positionCode":[0],"squadId":[802],"playerId":[80028],"scoreName":["goal"]},{"period":[2],"distanceCode":[0],"scorepoints":[1],"periodSeconds":[712],"positionCode":[1],"squadId":[802],"playerId":[80532],"scoreName":["goal"]},{"period":[2],"distanceCode":[0],"scorepoints":[1],"periodSeconds":[747],"positionCode":[1],"squadId":[802],"playerId":[80532],"scoreName":["goal"]},{"period":[2],"distanceCode":[0],"scorepoints":[1],"periodSeconds":[780],"positionCode":[2],"squadId":[802],"playerId":[80532],"scoreName":["goal"]},{"period":[2],"distanceCode":[0],"scorepoints":[0],"periodSeconds":[797],"positionCode":[2],"squadId":[8120],"playerId":[80229],"scoreName":["miss"]},{"period":[2],"distanceCode":[0],"scorepoints":[1],"periodSeconds":[842],"positionCode":[0],"squadId":[8120],"playerId":[80710],"scoreName":["goal"]},{"period":[2],"distanceCode":[0],"scorepoints":[1],"periodSeconds":[859],"positionCode":[1],"squadId":[802],"playerId":[80532],"scoreName":["goal"]},{"period":[2],"distanceCode":[0],"scorepoints":[1],"periodSeconds":[886],"positionCode":[2],"squadId":[802],"playerId":[80532],"scoreName":["goal"]},{"period":[3],"distanceCode":[0],"scorepoints":[1],"periodSeconds":[22],"positionCode":[2],"squadId":[8120],"playerId":[991906],"scoreName":["goal"]},{"period":[3],"distanceCode":[0],"scorepoints":[1],"periodSeconds":[94],"positionCode":[0],"squadId":[802],"playerId":[80532],"scoreName":["goal"]},{"period":[3],"distanceCode":[0],"scorepoints":[0],"periodSeconds":[118],"positionCode":[1],"squadId":[8120],"playerId":[80710],"scoreName":["miss"]},{"period":[3],"distanceCode":[0],"scorepoints":[1],"periodSeconds":[149],"positionCode":[0],"squadId":[8120],"playerId":[991906],"scoreName":["goal"]},{"period":[3],"distanceCode":[1],"scorepoints":[1],"periodSeconds":[166],"positionCode":[1],"squadId":[802],"playerId":[80532],"scoreName":["goal"]},{"period":[3],"distanceCode":[0],"scorepoints":[1],"periodSeconds":[219],"positionCode":[2],"squadId":[802],"playerId":[80532],"scoreName":["goal"]},{"period":[3],"distanceCode":[0],"scorepoints":[1],"periodSeconds":[289],"positionCode":[2],"squadId":[802],"playerId":[80532],"scoreName":["goal"]},{"period":[3],"distanceCode":[0],"scorepoints":[1],"periodSeconds":[320],"positionCode":[0],"squadId":[8120],"playerId":[80710],"scoreName":["goal"]},{"period":[3],"distanceCode":[1],"scorepoints":[1],"periodSeconds":[345],"positionCode":[1],"squadId":[802],"playerId":[80532],"scoreName":["goal"]},{"period":[3],"distanceCode":[0],"scorepoints":[1],"periodSeconds":[365],"positionCode":[0],"squadId":[802],"playerId":[80532],"scoreName":["goal"]},{"period":[3],"distanceCode":[0],"scorepoints":[1],"periodSeconds":[376],"positionCode":[0],"squadId":[802],"playerId":[80532],"scoreName":["goal"]},{"period":[3],"distanceCode":[0],"scorepoints":[1],"periodSeconds":[415],"positionCode":[0],"squadId":[8120],"playerId":[80710],"scoreName":["goal"]},{"period":[3],"distanceCode":[0],"scorepoints":[0],"periodSeconds":[459],"positionCode":[2],"squadId":[802],"playerId":[80532],"scoreName":["miss"]},{"period":[3],"distanceCode":[0],"scorepoints":[1],"periodSeconds":[476],"positionCode":[1],"squadId":[8120],"playerId":[80710],"scoreName":["goal"]},{"period":[3],"distanceCode":[0],"scorepoints":[1],"periodSeconds":[492],"positionCode":[0],"squadId":[8120],"playerId":[80710],"scoreName":["goal"]},{"period":[3],"distanceCode":[0],"scorepoints":[1],"periodSeconds":[536],"positionCode":[1],"squadId":[8120],"playerId":[80710],"scoreName":["goal"]},{"period":[3],"distanceCode":[0],"scorepoints":[1],"periodSeconds":[565],"positionCode":[2],"squadId":[8120],"playerId":[991906],"scoreName":["goal"]},{"period":[3],"distanceCode":[0],"scorepoints":[1],"periodSeconds":[605],"positionCode":[0],"squadId":[802],"playerId":[80028],"scoreName":["goal"]},{"period":[3],"distanceCode":[0],"scorepoints":[1],"periodSeconds":[633],"positionCode":[1],"squadId":[8120],"playerId":[80710],"scoreName":["goal"]},{"period":[3],"distanceCode":[0],"scorepoints":[0],"periodSeconds":[655],"positionCode":[2],"squadId":[802],"playerId":[80532],"scoreName":["miss"]},{"period":[3],"distanceCode":[0],"scorepoints":[1],"periodSeconds":[668],"positionCode":[1],"squadId":[8120],"playerId":[80710],"scoreName":["goal"]},{"period":[3],"distanceCode":[0],"scorepoints":[1],"periodSeconds":[687],"positionCode":[1],"squadId":[8120],"playerId":[80710],"scoreName":["goal"]},{"period":[3],"distanceCode":[0],"scorepoints":[1],"periodSeconds":[751],"positionCode":[0],"squadId":[802],"playerId":[80532],"scoreName":["goal"]},{"period":[3],"distanceCode":[0],"scorepoints":[1],"periodSeconds":[768],"positionCode":[1],"squadId":[8120],"playerId":[80710],"scoreName":["goal"]},{"period":[3],"distanceCode":[0],"scorepoints":[1],"periodSeconds":[833],"positionCode":[2],"squadId":[8120],"playerId":[80710],"scoreName":["goal"]},{"period":[3],"distanceCode":[0],"scorepoints":[0],"periodSeconds":[863],"positionCode":[0],"squadId":[802],"playerId":[80532],"scoreName":["miss"]},{"period":[3],"distanceCode":[0],"scorepoints":[1],"periodSeconds":[886],"positionCode":[2],"squadId":[8120],"playerId":[80710],"scoreName":["goal"]},{"period":[3],"distanceCode":[0],"scorepoints":[0],"periodSeconds":[898],"positionCode":[2],"squadId":[802],"playerId":[80532],"scoreName":["miss"]},{"period":[4],"distanceCode":[1],"scorepoints":[1],"periodSeconds":[30],"positionCode":[0],"squadId":[8120],"playerId":[80710],"scoreName":["goal"]},{"period":[4],"distanceCode":[1],"scorepoints":[1],"periodSeconds":[92],"positionCode":[1],"squadId":[802],"playerId":[80028],"scoreName":["goal"]},{"period":[4],"distanceCode":[0],"scorepoints":[1],"periodSeconds":[118],"positionCode":[2],"squadId":[8120],"playerId":[991906],"scoreName":["goal"]},{"period":[4],"distanceCode":[0],"scorepoints":[0],"periodSeconds":[133],"positionCode":[1],"squadId":[802],"playerId":[80532],"scoreName":["miss"]},{"period":[4],"distanceCode":[0],"scorepoints":[1],"periodSeconds":[133],"positionCode":[1],"squadId":[8120],"playerId":[80710],"scoreName":["goal"]},{"period":[4],"distanceCode":[0],"scorepoints":[1],"periodSeconds":[177],"positionCode":[0],"squadId":[8120],"playerId":[991906],"scoreName":["goal"]},{"period":[4],"distanceCode":[0],"scorepoints":[1],"periodSeconds":[187],"positionCode":[1],"squadId":[802],"playerId":[80532],"scoreName":["goal"]},{"period":[4],"distanceCode":[0],"scorepoints":[1],"periodSeconds":[211],"positionCode":[0],"squadId":[802],"playerId":[80532],"scoreName":["goal"]},{"period":[4],"distanceCode":[0],"scorepoints":[0],"periodSeconds":[235],"positionCode":[2],"squadId":[802],"playerId":[80532],"scoreName":["miss"]},{"period":[4],"distanceCode":[0],"scorepoints":[1],"periodSeconds":[269],"positionCode":[1],"squadId":[802],"playerId":[80028],"scoreName":["goal"]},{"period":[4],"distanceCode":[0],"scorepoints":[1],"periodSeconds":[288],"positionCode":[1],"squadId":[8120],"playerId":[80710],"scoreName":["goal"]},{"period":[4],"distanceCode":[0],"scorepoints":[1],"periodSeconds":[303],"positionCode":[2],"squadId":[802],"playerId":[80532],"scoreName":["goal"]},{"period":[4],"distanceCode":[1],"scorepoints":[1],"periodSeconds":[337],"positionCode":[1],"squadId":[8120],"playerId":[991906],"scoreName":["goal"]},{"period":[4],"distanceCode":[0],"scorepoints":[0],"periodSeconds":[352],"positionCode":[0],"squadId":[802],"playerId":[80028],"scoreName":["miss"]},{"period":[4],"distanceCode":[0],"scorepoints":[0],"periodSeconds":[376],"positionCode":[2],"squadId":[8120],"playerId":[991906],"scoreName":["miss"]},{"period":[4],"distanceCode":[0],"scorepoints":[1],"periodSeconds":[382],"positionCode":[1],"squadId":[8120],"playerId":[80710],"scoreName":["goal"]},{"period":[4],"distanceCode":[0],"scorepoints":[1],"periodSeconds":[404],"positionCode":[0],"squadId":[8120],"playerId":[80710],"scoreName":["goal"]},{"period":[4],"distanceCode":[0],"scorepoints":[1],"periodSeconds":[432],"positionCode":[0],"squadId":[802],"playerId":[80028],"scoreName":["goal"]},{"period":[4],"distanceCode":[0],"scorepoints":[0],"periodSeconds":[459],"positionCode":[1],"squadId":[8120],"playerId":[80710],"scoreName":["miss"]},{"period":[4],"distanceCode":[0],"scorepoints":[0],"periodSeconds":[503],"positionCode":[1],"squadId":[802],"playerId":[80028],"scoreName":["miss"]},{"period":[4],"distanceCode":[0],"scorepoints":[0],"periodSeconds":[542],"positionCode":[1],"squadId":[8120],"playerId":[80710],"scoreName":["miss"]},{"period":[4],"distanceCode":[0],"scorepoints":[1],"periodSeconds":[546],"positionCode":[0],"squadId":[8120],"playerId":[80710],"scoreName":["goal"]},{"period":[4],"distanceCode":[0],"scorepoints":[1],"periodSeconds":[570],"positionCode":[1],"squadId":[802],"playerId":[80028],"scoreName":["goal"]},{"period":[4],"distanceCode":[0],"scorepoints":[0],"periodSeconds":[653],"positionCode":[0],"squadId":[8120],"playerId":[991906],"scoreName":["miss"]},{"period":[4],"distanceCode":[0],"scorepoints":[1],"periodSeconds":[665],"positionCode":[2],"squadId":[8120],"playerId":[80710],"scoreName":["goal"]},{"period":[4],"distanceCode":[0],"scorepoints":[1],"periodSeconds":[682],"positionCode":[2],"squadId":[802],"playerId":[80532],"scoreName":["goal"]},{"period":[4],"distanceCode":[0],"scorepoints":[1],"periodSeconds":[713],"positionCode":[0],"squadId":[8120],"playerId":[80710],"scoreName":["goal"]},{"period":[4],"distanceCode":[0],"scorepoints":[1],"periodSeconds":[740],"positionCode":[2],"squadId":[802],"playerId":[80028],"scoreName":["goal"]},{"period":[4],"distanceCode":[0],"scorepoints":[1],"periodSeconds":[755],"positionCode":[2],"squadId":[8120],"playerId":[80710],"scoreName":["goal"]},{"period":[4],"distanceCode":[0],"scorepoints":[1],"periodSeconds":[790],"positionCode":[2],"squadId":[802],"playerId":[80028],"scoreName":["goal"]},{"period":[4],"distanceCode":[0],"scorepoints":[1],"periodSeconds":[825],"positionCode":[1],"squadId":[802],"playerId":[80532],"scoreName":["goal"]},{"period":[4],"distanceCode":[0],"scorepoints":[1],"periodSeconds":[847],"positionCode":[1],"squadId":[802],"playerId":[80532],"scoreName":["goal"]},{"period":[4],"distanceCode":[0],"scorepoints":[1],"periodSeconds":[870],"positionCode":[1],"squadId":[8120],"playerId":[80710],"scoreName":["goal"]},{"period":[4],"distanceCode":[0],"scorepoints":[1],"periodSeconds":[882],"positionCode":[0],"squadId":[802],"playerId":[80532],"scoreName":["goal"]}]}}
